Workbook

Sheet Summary
A1: Local Government TAM — National Summary
A2: Counts and estimated annual operating spend by state and population bucket. School districts excluded.
A3: Source: 2022 Census of Governments + Annual Survey of State and Local Govt Finances. Refreshed 2026-05-01.
A5: ENTITY COUNT BY STATE × BUCKET (counties + munis + townships)
A6: State | B6: <1K | C6: 1K-5K | D6: 5K-10K | E6: 10K-20K | F6: 20K-50K | G6: 50K-100K | H6: 100K+ | I6: Special Districts | J6: TOTAL ENTITIES | K6: TOTAL TAM ($M)
A7: AL | B7: 179 | C7: 153 | D7: 62 | E7: 53 | F7: 46 | G7: 20 | H7: 15 | I7: 540 | J7: =SUM(B7:I7) | K7: ='AL'!B22/1000000
A8: AK | B8: 66 | C8: 50 | D8: 17 | E8: 13 | F8: 10 | G8: 4 | H8: 2 | I8: 15 | J8: =SUM(B8:I8) | K8: ='AK'!B22/1000000
A9: AZ | B9: 27 | C9: 27 | D9: 13 | E9: 12 | F9: 13 | G9: 7 | H9: 7 | I9: 318 | J9: =SUM(B9:I9) | K9: ='AZ'!B22/1000000
A10: AR | B10: 195 | C10: 167 | D10: 68 | E10: 58 | F10: 51 | G10: 21 | H10: 17 | I10: 723 | J10: =SUM(B10:I10) | K10: ='AR'!B22/1000000
A11: CA | B11: 111 | C11: 123 | D11: 66 | E11: 72 | F11: 82 | G11: 43 | H11: 43 | I11: 2767 | J11: =SUM(B11:I11) | K11: ='CA'!B22/1000000
A12: CO | B12: 81 | C12: 82 | D12: 41 | E12: 39 | F12: 44 | G12: 23 | H12: 23 | I12: 2540 | J12: =SUM(B12:I12) | K12: ='CO'!B22/1000000
A13: CT | B13: 77 | C13: 58 | D13: 19 | E13: 12 | F13: 9 | G13: 3 | H13: 1 | I13: 460 | J13: =SUM(B13:I13) | K13: ='CT'!B22/1000000
A14: DE | B14: 17 | C14: 17 | D14: 7 | E14: 6 | F14: 7 | G14: 3 | H14: 3 | I14: 256 | J14: =SUM(B14:I14) | K14: ='DE'!B22/1000000
A15: FL | B15: 95 | C15: 107 | D15: 57 | E15: 62 | F15: 74 | G15: 41 | H15: 42 | I15: 1134 | J15: =SUM(B15:I15) | K15: ='FL'!B22/1000000
A16: GA | B16: 189 | C16: 173 | D16: 81 | E16: 80 | F16: 83 | G16: 42 | H16: 42 | I16: 720 | J16: =SUM(B16:I16) | K16: ='GA'!B22/1000000
A17: HI | B17: 1 | C17: 0 | D17: 0 | E17: 0 | F17: 1 | G17: 1 | H17: 1 | I17: 17 | J17: =SUM(B17:I17) | K17: ='HI'!B22/1000000
A18: ID | B18: 78 | C18: 68 | D18: 29 | E18: 26 | F18: 24 | G18: 11 | H18: 8 | I18: 1058 | J18: =SUM(B18:I18) | K18: ='ID'!B22/1000000
A19: IL | B19: 864 | C19: 791 | D19: 342 | E19: 297 | F19: 295 | G19: 142 | H19: 100 | I19: 3050 | J19: =SUM(B19:I19) | K19: ='IL'!B22/1000000
A20: IN | B20: 703 | C20: 499 | D20: 169 | E20: 122 | F20: 100 | G20: 43 | H20: 29 | I20: 1262 | J20: =SUM(B20:I20) | K20: ='IN'!B22/1000000
A21: IA | B21: 422 | C21: 317 | D21: 115 | E21: 87 | F21: 64 | G21: 21 | H21: 14 | I21: 562 | J21: =SUM(B21:I21) | K21: ='IA'!B22/1000000
A22: KS | B22: 1007 | C22: 606 | D22: 171 | E22: 106 | F22: 70 | G22: 23 | H22: 12 | I22: 1535 | J22: =SUM(B22:I22) | K22: ='KS'!B22/1000000
A23: KY | B23: 162 | C23: 146 | D23: 64 | E23: 58 | F23: 57 | G23: 27 | H23: 22 | I23: 720 | J23: =SUM(B23:I23) | K23: ='KY'!B22/1000000
A24: LA | B24: 118 | C24: 104 | D24: 43 | E24: 38 | F24: 35 | G24: 15 | H24: 11 | I24: 95 | J24: =SUM(B24:I24) | K24: ='LA'!B22/1000000
A25: ME | B25: 278 | C25: 154 | D25: 37 | E25: 20 | F25: 12 | G25: 3 | H25: 1 | I25: 226 | J25: =SUM(B25:I25) | K25: ='ME'!B22/1000000
A26: MD | B26: 47 | C26: 46 | D26: 22 | E26: 22 | F26: 22 | G26: 10 | H26: 11 | I26: 90 | J26: =SUM(B26:I26) | K26: ='MD'!B22/1000000
A27: MA | B27: 130 | C27: 109 | D27: 42 | E27: 31 | F27: 26 | G27: 13 | H27: 5 | I27: 480 | J27: =SUM(B27:I27) | K27: ='MA'!B22/1000000
A28: MI | B28: 807 | C28: 564 | D28: 185 | E28: 129 | F28: 101 | G28: 42 | H28: 28 | I28: 451 | J28: =SUM(B28:I28) | K28: ='MI'!B22/1000000
A29: MN | B29: 1191 | C29: 833 | D29: 271 | E29: 189 | F29: 144 | G29: 59 | H29: 34 | I29: 482 | J29: =SUM(B29:I29) | K29: ='MN'!B22/1000000
A30: MS | B30: 116 | C30: 103 | D30: 45 | E30: 42 | F30: 40 | G30: 18 | H30: 15 | I30: 467 | J30: =SUM(B30:I30) | K30: ='MS'!B22/1000000
A31: MO | B31: 491 | C31: 395 | D31: 156 | E31: 130 | F31: 115 | G31: 51 | H31: 42 | I31: 1620 | J31: =SUM(B31:I31) | K31: ='MO'!B22/1000000
A32: MT | B32: 58 | C32: 49 | D32: 22 | E32: 21 | F32: 18 | G32: 7 | H32: 6 | I32: 813 | J32: =SUM(B32:I32) | K32: ='MT'!B22/1000000
A33: NE | B33: 477 | C33: 312 | D33: 100 | E33: 70 | F33: 52 | G33: 17 | H33: 10 | I33: 1300 | J33: =SUM(B33:I33) | K33: ='NE'!B22/1000000
A34: NV | B34: 6 | C34: 6 | D34: 4 | E34: 4 | F34: 6 | G34: 4 | H34: 5 | I34: 175 | J34: =SUM(B34:I34) | K34: ='NV'!B22/1000000
A35: NH | B35: 121 | C35: 76 | D35: 21 | E35: 12 | F35: 9 | G35: 4 | H35: 1 | I35: 142 | J35: =SUM(B35:I35) | K35: ='NH'!B22/1000000
A36: NJ | B36: 130 | C36: 143 | D36: 75 | E36: 77 | F36: 84 | G36: 41 | H36: 36 | I36: 281 | J36: =SUM(B36:I36) | K36: ='NJ'!B22/1000000
A37: NM | B37: 41 | C37: 37 | D37: 16 | E37: 15 | F37: 16 | G37: 7 | H37: 6 | I37: 685 | J37: =SUM(B37:I37) | K37: ='NM'!B22/1000000
A38: NY | B38: 510 | C38: 457 | D38: 192 | E38: 162 | F38: 158 | G38: 76 | H38: 49 | I38: 1183 | J38: =SUM(B38:I38) | K38: ='NY'!B22/1000000
A39: NC | B39: 194 | C39: 174 | D39: 77 | E39: 72 | F39: 70 | G39: 34 | H39: 31 | I39: 311 | J39: =SUM(B39:I39) | K39: ='NC'!B22/1000000
A40: ND | B40: 912 | C40: 526 | D40: 138 | E40: 77 | F40: 47 | G40: 14 | H40: 7 | I40: 763 | J40: =SUM(B40:I40) | K40: ='ND'!B22/1000000
A41: OH | B41: 983 | C41: 707 | D41: 240 | E41: 174 | F41: 137 | G41: 56 | H41: 36 | I41: 776 | J41: =SUM(B41:I41) | K41: ='OH'!B22/1000000
A42: OK | B42: 232 | C42: 198 | D42: 79 | E42: 67 | F42: 58 | G42: 24 | H42: 18 | I42: 560 | J42: =SUM(B42:I42) | K42: ='OK'!B22/1000000
A43: OR | B43: 86 | C43: 75 | D43: 33 | E43: 30 | F43: 28 | G43: 13 | H43: 12 | I43: 1057 | J43: =SUM(B43:I43) | K43: ='OR'!B22/1000000
A44: PA | B44: 1129 | C44: 805 | D44: 268 | E44: 190 | F44: 145 | G44: 57 | H44: 34 | I44: 1620 | J44: =SUM(B44:I44) | K44: ='PA'!B22/1000000
A45: RI | B45: 17 | C45: 12 | D45: 4 | E45: 3 | F45: 2 | G45: 1 | H45: 0 | I45: 84 | J45: =SUM(B45:I45) | K45: ='RI'!B22/1000000
A46: SC | B46: 95 | C46: 85 | D46: 38 | E46: 35 | F46: 34 | G46: 16 | H46: 14 | I46: 297 | J46: =SUM(B46:I46) | K46: ='SC'!B22/1000000
A47: SD | B47: 669 | C47: 394 | D47: 107 | E47: 65 | F47: 42 | G47: 13 | H47: 8 | I47: 350 | J47: =SUM(B47:I47) | K47: ='SD'!B22/1000000
A48: TN | B48: 122 | C48: 110 | D48: 51 | E48: 51 | F48: 52 | G48: 26 | H48: 25 | I48: 525 | J48: =SUM(B48:I48) | K48: ='TN'!B22/1000000
A49: TX | B49: 366 | C49: 366 | D49: 179 | E49: 174 | F49: 192 | G49: 98 | H49: 100 | I49: 3100 | J49: =SUM(B49:I49) | K49: ='TX'!B22/1000000
A50: UT | B50: 74 | C50: 73 | D50: 35 | E50: 32 | F50: 33 | G50: 15 | H50: 15 | I50: 1129 | J50: =SUM(B50:I50) | K50: ='UT'!B22/1000000
A51: VT | B51: 157 | C51: 90 | D51: 24 | E51: 13 | F51: 9 | G51: 4 | H51: 1 | I51: 156 | J51: =SUM(B51:I51) | K51: ='VT'!B22/1000000
A52: VA | B52: 81 | C52: 77 | D52: 37 | E52: 39 | F52: 43 | G52: 23 | H52: 24 | I52: 195 | J52: =SUM(B52:I52) | K52: ='VA'!B22/1000000
A53: WA | B53: 84 | C53: 83 | D53: 40 | E53: 37 | F53: 39 | G53: 18 | H53: 19 | I53: 1336 | J53: =SUM(B53:I53) | K53: ='WA'!B22/1000000
A54: WV | B54: 90 | C54: 80 | D54: 35 | E54: 30 | F54: 28 | G54: 13 | H54: 11 | I54: 358 | J54: =SUM(B54:I54) | K54: ='WV'!B22/1000000
A55: WI | B55: 836 | C55: 587 | D55: 192 | E55: 135 | F55: 105 | G55: 42 | H55: 26 | I55: 730 | J55: =SUM(B55:I55) | K55: ='WI'!B22/1000000
A56: WY | B56: 44 | C56: 35 | D56: 14 | E56: 12 | F56: 10 | G56: 4 | H56: 3 | I56: 683 | J56: =SUM(B56:I56) | K56: ='WY'!B22/1000000
A57: DC | B57: 0 | C57: 1 | D57: 0 | E57: 0 | F57: 0 | G57: 0 | H57: 0 | I57: 1 | J57: =SUM(B57:I57) | K57: ='DC'!B22/1000000
A58: US TOTAL | B58: =SUM(B7:B57) | C58: =SUM(C7:C57) | D58: =SUM(D7:D57) | E58: =SUM(E7:E57) | F58: =SUM(F7:F57) | G58: =SUM(G7:G57) | H58: =SUM(H7:H57) | I58: =SUM(I7:I57) | ... K58: =SUM(K7:K57)
A60: ESTIMATED ANNUAL OPERATING SPEND ($M) BY STATE × BUCKET
A61: State | B61: <1K | C61: 1K-5K | D61: 5K-10K | E61: 10K-20K | F61: 20K-50K | G61: 50K-100K | H61: 100K+ | I61: Special Districts | J61: TOTAL SPEND ($M)
A62: AL | B62: 137.5 | C62: 890.7 | D62: 1117.1 | E62: 2083.7 | F62: 4508.5 | G62: 4760 | H62: 13090 | I62: 3488.4 | J62: =SUM(B62:I62)
A63: AK | B63: 74.2 | C63: 427.3 | D63: 450.9 | E63: 754.2 | F63: 1426 | G63: 1400 | H63: 2887.5 | I63: 142.5 | J63: =SUM(B63:I63)
A64: AZ | B64: 23.1 | C64: 175.2 | D64: 262.4 | E64: 537.3 | F64: 1454.8 | G64: 1915.2 | H64: 7315 | I64: 2296 | J64: =SUM(B64:I64)
A65: AR | B65: 140.9 | C65: 915.6 | D65: 1153 | E65: 2148.2 | F65: 4667.4 | G65: 4659.2 | H65: 14168 | I65: 4395.8 | J65: =SUM(B65:I65)
A66: CA | B66: 144.9 | C66: 1210.1 | D66: 2034.3 | E66: 4985.7 | F66: 14604.3 | G66: 19000.8 | H66: 77038.5 | I66: 30492.3 | J66: =SUM(B66:I66)
A67: CO | B67: 76.5 | C67: 590.2 | D67: 912.5 | E67: 1900.7 | F67: 5338.2 | G67: 6703.2 | H67: 25063.5 | I67: 20269.2 | J67: =SUM(B67:I67)
A68: CT | B68: 33.1 | C68: 208.2 | D68: 252.9 | E68: 404.2 | F68: 860.2 | G68: 717.5 | H68: 1925 | I68: 4370 | J68: =SUM(B68:I68)
A69: DE | B69: 15.3 | C69: 114.8 | D69: 149.1 | E69: 294 | F69: 871.1 | G69: 896 | H69: 3850 | I69: 1945.6 | J69: =SUM(B69:I69)
A70: FL | B70: 85.5 | C70: 728.7 | D70: 1211.3 | E70: 2948.4 | F70: 8949.7 | G70: 12208 | H70: 49280 | I70: 8618.4 | J70: =SUM(B70:I70)
A71: GA | B71: 153.7 | C71: 1074.3 | D71: 1541.9 | E71: 3265.9 | F71: 8275.1 | G71: 10080 | H71: 36729 | I71: 4924.8 | J71: =SUM(B71:I71)
A72: HI | B72: 1.4 | C72: 0 | D72: 0 | E72: 0 | F72: 134.8 | G72: 336 | H72: 1155 | I72: 193.8 | J72: =SUM(B72:I72)
A73: ID | B73: 67.3 | C73: 446.3 | D73: 582.8 | E73: 1125.2 | F73: 2547.4 | G73: 2766.4 | H73: 7315 | I73: 7638.8 | J73: =SUM(B73:I73)
... A112: DC | B112: 0 | C112: 9.4 | D112: 0 | E112: 0 | F112: 0 | G112: 0 | H112: 0 | I112: 10.6 | J112: =SUM(B112:I112)
A113: US TOTAL | B113: =SUM(B62:B112) | C113: =SUM(C62:C112) | D113: =SUM(D62:D112) | E113: =SUM(E62:E112) | F113: =SUM(F62:F112) | G113: =SUM(G62:G112) | H113: =SUM(H62:H112) | I113: =SUM(I62:I112) | J113: =SUM(J62:J112)

Sheet Methodology
A1: Methodology
A3: Scope
A4: U.S. local-government software market. Entity types tracked: counties / parishes, incorporated municipalities, organized townships, special districts. School districts and federal/state agencies are excluded.
A6: Population buckets
A7: <1K, 1K-5K, 5K-10K, 10K-20K, 20K-50K, 50K-100K, 100K+. Applied to munis, counties, and townships. Special districts are not population-bucketed (size driven by purpose — water, fire, transit — not by population).
A9: Entity counts
A10: Sourced from the 2022 Census of Governments. Per-state counts encoded in data.py. National totals reconcile to Census within ~1-3% (rounding from compilation of state-by-state filings).
A12: Bucket distribution
A13: National baseline distribution per entity type, multiplied by state-level skew profiles (urban_strong / urban_mild / balanced / rural_mild / rural_strong) and renormalized so each state's distribution sums to 100% per entity type.
A15: Spend math
A16: TAM_per_cell = entity_count × avg_bucket_population × per_capita_spend. Per-capita spend is anchored to Census Annual Survey of State and Local Government Finances 2022. Special district spend uses a flat $7.6M average annual operating spend per district. National total lands within ±10% of Census $2.2T figure; deviation reflects the fact that this TAM model counts each entity's spend independently (reflects software customer count) rather than netting overlapping jurisdictions.
A18: Color coding
... A28: Each vendor's published customer total is allocated across states using HQ-state weighting, named case-study customers, acquired-company home/service states, state-specific marketing presence, and a population-weighted residual. Per-state sums calibrated to land within ±15% of each vendor's published total.

Sheet AL
A1: AL — Alabama
A2: Counts and estimated annual operating spend by entity type and bucket.
A4: Entity / Bucket | B4: Count | C4: Avg Pop | D4: $/capita | E4: Spend ($)
A5: Municipalities
A6: <1K | B6: 178 | C6: 450 | D6: 2000 | E6: 160200000
A7: 1K-5K | B7: 146 | C7: 2700 | D7: 2500 | E7: 985500000
A8: 5K-10K | B8: 53 | C8: 7100 | D8: 3000 | E8: 1128900000
A9: 10K-20K | B9: 40 | C9: 14000 | D9: 3500 | E9: 1960000000
A10: 20K-50K | B10: 29 | C10: 31000 | D10: 4200 | E10: 3775800000
A11: 50K-100K | B11: 10 | C11: 70000 | D11: 4800 | E11: 3360000000
A12: 100K+ | B12: 5 | C12: 220000 | D12: 7000 | E12: 7700000000
A13: Municipalities subtotal | B13: 461 | E13: 19070400000
A15: Counties / Parishes
A16: <1K | B16: 1 | C16: 450 | D16: 3500 | E16: 1575000
A17: 1K-5K | B17: 7 | C17: 2700 | D17: 3300 | E17: 62370000
A18: 5K-10K | B18: 9 | C18: 7100 | D18: 2900 | E18: 185310000
A19: 10K-20K | B19: 13 | C19: 14000 | D19: 2700 | E19: 491400000
A20: 20K-50K | B20: 17 | C20: 31000 | D20: 2900 | E20: 1528300000
A21: 50K-100K | B21: 10 | C21: 70000 | D21: 3200 | E21: 2240000000
A22: GRAND TOTAL | B22: =B13+B23+B27 | C22: 220000 | D22: 3500 | E22: =E13+E23+E27
A23: Counties / Parishes subtotal | B23: =SUM(B16:B22) | E23: =SUM(E16:E22)
A25: Special Districts
A26: (all sizes) | B26: 540 | D26: 7600000 | E26: 4104000000
A27: Special Districts subtotal | B27: 540 | E27: 4104000000

Sheet AK
A1: AK — Alaska
A2: Counts and estimated annual operating spend by entity type and bucket.
A4: Entity / Bucket | B4: Count | C4: Avg Pop | D4: $/capita | E4: Spend ($)
A5: Municipalities
A6: <1K | B6: 66 | C6: 450 | D6: 2000 | E6: 59400000
A7: 1K-5K | B7: 48 | C7: 2700 | D7: 2500 | E7: 324000000
A8: 5K-10K | B8: 15 | C8: 7100 | D8: 3000 | E8: 319500000
A9: 10K-20K | B9: 10 | C9: 14000 | D9: 3500 | E9: 490000000
A10: 20K-50K | B10: 6 | C10: 31000 | D10: 4200 | E10: 781200000
A11: 50K-100K | B11: 2 | C11: 70000 | D11: 4800 | E11: 672000000
A12: 100K+ | B12: 1 | C12: 220000 | D12: 7000 | E12: 1540000000
A13: Municipalities subtotal | B13: 148 | E13: 4186100000
A15: Counties / Parishes
A16: <1K | B16: 0 | C16: 450 | D16: 3500 | E16: 0
A17: 1K-5K | B17: 2 | C17: 2700 | D17: 3300 | E17: 17820000
A18: 5K-10K | B18: 2 | C18: 7100 | D18: 2900 | E18: 41180000
A19: 10K-20K | B19: 3 | C19: 14000 | D19: 2700 | E19: 113400000
A20: 20K-50K | B20: 4 | C20: 31000 | D20: 2900 | E20: 359600000
A21: 50K-100K | B21: 2 | C21: 70000 | D21: 3200 | E21: 448000000
A22: GRAND TOTAL | B22: =B13+B23+B27 | C22: 220000 | D22: 3500 | E22: =E13+E23+E27
A23: Counties / Parishes subtotal | B23: =SUM(B16:B22) | E23: =SUM(E16:E22)
A25: Special Districts
A26: (all sizes) | B26: 15 | D26: 7600000 | E26: 114000000
A27: Special Districts subtotal | B27: 15 | E27: 114000000

Sheet AZ
A1: AZ — Arizona
A2: Counts and estimated annual operating spend by entity type and bucket.
A4: Entity / Bucket | B4: Count | C4: Avg Pop | D4: $/capita | E4: Spend ($)
A5: Municipalities
A6: <1K | B6: 27 | C6: 450 | D6: 2000 | E6: 24300000
A7: 1K-5K | B7: 26 | C7: 2700 | D7: 2500 | E7: 175500000
A8: 5K-10K | B8: 12 | C8: 7100 | D8: 3000 | E8: 255600000
A9: 10K-20K | B9: 10 | C9: 14000 | D9: 3500 | E9: 490000000
A10: 20K-50K | B10: 9 | C10: 31000 | D10: 4200 | E10: 1171800000
A11: 50K-100K | B11: 4 | C11: 70000 | D11: 4800 | E11: 1344000000
A12: 100K+ | B12: 3 | C12: 220000 | D12: 7000 | E12: 4620000000
A13: Municipalities subtotal | B13: 91 | E13: 8081200000
A15: Counties / Parishes
A16: <1K | B16: 0 | C16: 450 | D16: 3500 | E16: 0
A17: 1K-5K | B17: 1 | C17: 2700 | D17: 3300 | E17: 8910000
A18: 5K-10K | B18: 1 | C18: 7100 | D18: 2900 | E18: 20590000
A19: 10K-20K | B19: 2 | C19: 14000 | D19: 2700 | E19: 75600000
A20: 20K-50K | B20: 4 | C20: 31000 | D20: 2900 | E20: 359600000
A21: 50K-100K | B21: 3 | C21: 70000 | D21: 3200 | E21: 672000000
A22: GRAND TOTAL | B22: =B13+B23+B27 | C22: 220000 | D22: 3500 | E22: =E13+E23+E27
A23: Counties / Parishes subtotal | B23: =SUM(B16:B22) | E23: =SUM(E16:E22)
A25: Special Districts
A26: (all sizes) | B26: 318 | D26: 7600000 | E26: 2416800000
A27: Special Districts subtotal | B27: 318 | E27: 2416800000

Sheet AR
A1: AR — Arkansas
A2: Counts and estimated annual operating spend by entity type and bucket.
A4: Entity / Bucket | B4: Count | C4: Avg Pop | D4: $/capita | E4: Spend ($)
A5: Municipalities
A6: <1K | B6: 194 | C6: 450 | D6: 2000 | E6: 174600000
A7: 1K-5K | B7: 159 | C7: 2700 | D7: 2500 | E7: 1073250000
A8: 5K-10K | B8: 58 | C8: 7100 | D8: 3000 | E8: 1235400000
A9: 10K-20K | B9: 44 | C9: 14000 | D9: 3500 | E9: 2156000000
A10: 20K-50K | B10: 31 | C10: 31000 | D10: 4200 | E10: 4036200000
A11: 50K-100K | B11: 10 | C11: 70000 | D11: 4800 | E11: 3360000000
A12: 100K+ | B12: 6 | C12: 220000 | D12: 7000 | E12: 9240000000
A13: Municipalities subtotal | B13: 502 | E13: 21275450000
A15: Counties / Parishes
A16: <1K | B16: 1 | C16: 450 | D16: 3500 | E16: 1575000
A17: 1K-5K | B17: 8 | C17: 2700 | D17: 3300 | E17: 71280000
A18: 5K-10K | B18: 10 | C18: 7100 | D18: 2900 | E18: 205900000
A19: 10K-20K | B19: 14 | C19: 14000 | D19: 2700 | E19: 529200000
A20: 20K-50K | B20: 20 | C20: 31000 | D20: 2900 | E20: 1798000000
A21: 50K-100K | B21: 11 | C21: 70000 | D21: 3200 | E21: 2464000000
A22: GRAND TOTAL | B22: =B13+B23+B27 | C22: 220000 | D22: 3500 | E22: =E13+E23+E27
A23: Counties / Parishes subtotal | B23: =SUM(B16:B22) | E23: =SUM(E16:E22)
A25: Special Districts
A26: (all sizes) | B26: 723 | D26: 7600000 | E26: 5494800000
A27: Special Districts subtotal | B27: 723 | E27: 5494800000

Sheet CA
A1: CA — California
A2: Counts and estimated annual operating spend by entity type and bucket.
A4: Entity / Bucket | B4: Count | C4: Avg Pop | D4: $/capita | E4: Spend ($)
A5: Municipalities
A6: <1K | B6: 111 | C6: 450 | D6: 2000 | E6: 99900000
A7: 1K-5K | B7: 121 | C7: 2700 | D7: 2500 | E7: 816750000
A8: 5K-10K | B8: 62 | C8: 7100 | D8: 3000 | E8: 1320600000
A9: 10K-20K | B9: 64 | C9: 14000 | D9: 3500 | E9: 3136000000
A10: 20K-50K | B10: 67 | C10: 31000 | D10: 4200 | E10: 8723400000
A11: 50K-100K | B11: 31 | C11: 70000 | D11: 4800 | E11: 10416000000
A12: 100K+ | B12: 26 | C12: 220000 | D12: 7000 | E12: 40040000000
A13: Municipalities subtotal | B13: 482 | E13: 64552650000
A15: Counties / Parishes
A16: <1K | B16: 0 | C16: 450 | D16: 3500 | E16: 0
A17: 1K-5K | B17: 2 | C17: 2700 | D17: 3300 | E17: 17820000
A18: 5K-10K | B18: 4 | C18: 7100 | D18: 2900 | E18: 82360000
A19: 10K-20K | B19: 8 | C19: 14000 | D19: 2700 | E19: 302400000
A20: 20K-50K | B20: 15 | C20: 31000 | D20: 2900 | E20: 1348500000
A21: 50K-100K | B21: 12 | C21: 70000 | D21: 3200 | E21: 2688000000
A22: GRAND TOTAL | B22: =B13+B23+B27 | C22: 220000 | D22: 3500 | E22: =E13+E23+E27
A23: Counties / Parishes subtotal | B23: =SUM(B16:B22) | E23: =SUM(E16:E22)
A25: Special Districts
A26: (all sizes) | B26: 2767 | D26: 7600000 | E26: 21029200000
A27: Special Districts subtotal | B27: 2767 | E27: 21029200000

Sheet CO
A1: CO — Colorado
A2: Counts and estimated annual operating spend by entity type and bucket.
A4: Entity / Bucket | B4: Count | C4: Avg Pop | D4: $/capita | E4: Spend ($)
A5: Municipalities
A6: <1K | B6: 81 | C6: 450 | D6: 2000 | E6: 72900000
A7: 1K-5K | B7: 78 | C7: 2700 | D7: 2500 | E7: 526500000
A8: 5K-10K | B8: 35 | C8: 7100 | D8: 3000 | E8: 745500000
A9: 10K-20K | B9: 30 | C9: 14000 | D9: 3500 | E9: 1470000000
A10: 20K-50K | B10: 28 | C10: 31000 | D10: 4200 | E10: 3645600000
A11: 50K-100K | B11: 11 | C11: 70000 | D11: 4800 | E11: 3696000000
A12: 100K+ | B12: 8 | C12: 220000 | D12: 7000 | E12: 12320000000
A13: Municipalities subtotal | B13: 271 | E13: 22476500000
A15: Counties / Parishes
A16: <1K | B16: 0 | C16: 450 | D16: 3500 | E16: 0
A17: 1K-5K | B17: 4 | C17: 2700 | D17: 3300 | E17: 35640000
A18: 5K-10K | B18: 6 | C18: 7100 | D18: 2900 | E18: 123540000
A19: 10K-20K | B19: 9 | C19: 14000 | D19: 2700 | E19: 340200000
A20: 20K-50K | B20: 16 | C20: 31000 | D20: 2900 | E20: 1438400000
A21: 50K-100K | B21: 12 | C21: 70000 | D21: 3200 | E21: 2688000000
A22: GRAND TOTAL | B22: =B13+B23+B27 | C22: 220000 | D22: 3500 | E22: =E13+E23+E27
A23: Counties / Parishes subtotal | B23: =SUM(B16:B22) | E23: =SUM(E16:E22)
A25: Special Districts
A26: (all sizes) | B26: 2540 | D26: 7600000 | E26: 19304000000
A27: Special Districts subtotal | B27: 2540 | E27: 19304000000

Sheet CT
A1: CT — Connecticut
A2: Counts and estimated annual operating spend by entity type and bucket.
A4: Entity / Bucket | B4: Count | C4: Avg Pop | D4: $/capita | E4: Spend ($)
A5: Municipalities
A6: <1K | B6: 9 | C6: 450 | D6: 2000 | E6: 8100000
A7: 1K-5K | B7: 9 | C7: 2700 | D7: 2500 | E7: 60750000
A8: 5K-10K | B8: 4 | C8: 7100 | D8: 3000 | E8: 85200000
A9: 10K-20K | B9: 3 | C9: 14000 | D9: 3500 | E9: 147000000
A10: 20K-50K | B10: 3 | C10: 31000 | D10: 4200 | E10: 390600000
A11: 50K-100K | B11: 1 | C11: 70000 | D11: 4800 | E11: 336000000
A12: 100K+ | B12: 1 | C12: 220000 | D12: 7000 | E12: 1540000000
A13: Municipalities subtotal | B13: 30 | E13: 2567650000
A15: Counties / Parishes
A16: <1K | B16: 0 | C16: 450 | D16: 3500 | E16: 0
A17: 1K-5K | B17: 0 | C17: 2700 | D17: 3300 | E17: 0
A18: 5K-10K | B18: 0 | C18: 7100 | D18: 2900 | E18: 0
A19: 10K-20K | B19: 0 | C19: 14000 | D19: 2700 | E19: 0
A20: 20K-50K | B20: 0 | C20: 31000 | D20: 2900 | E20: 0
A21: 50K-100K | B21: 0 | C21: 70000 | D21: 3200 | E21: 0
A22: GRAND TOTAL | B22: =B13+B23+B33+B37 | C22: 220000 | D22: 3500 | E22: =E13+E23+E33+E37
A23: Counties / Parishes subtotal | B23: =SUM(B16:B22) | E23: =SUM(E16:E22)
A25: Townships
A26: <1K | B26: 68 | C26: 450 | D26: 600 | E26: 18360000
A27: 1K-5K | B27: 49 | C27: 2700 | D27: 800 | E27: 105840000
A28: 5K-10K | B28: 15 | C28: 7100 | D28: 1100 | E28: 117150000
A29: 10K-20K | B29: 9 | C29: 14000 | D29: 1400 | E29: 176400000
A30: 20K-50K | B30: 6 | C30: 31000 | D30: 1600 | E30: 297600000
A31: 50K-100K | B31: 2 | C31: 70000 | D31: 1700 | E31: 238000000
A32: 100K+ | B32: 0 | C32: 220000 | D32: 1800 | E32: 0
A33: Townships subtotal | B33: 149 | E33: 953350000
A35: Special Districts
A36: (all sizes) | B36: 460 | D36: 7600000 | E36: 3496000000
A37: Special Districts subtotal | B37: 460 | E37: 3496000000

Sheet DE
A1: DE — Delaware
A2: Counts and estimated annual operating spend by entity type and bucket.
A4: Entity / Bucket | B4: Count | C4: Avg Pop | D4: $/capita | E4: Spend ($)
A5: Municipalities
A6: <1K | B6: 17 | C6: 450 | D6: 2000 | E6: 15300000
A7: 1K-5K | B7: 17 | C7: 2700 | D7: 2500 | E7: 114750000
A8: 5K-10K | B8: 7 | C8: 7100 | D8: 3000 | E8: 149100000
A9: 10K-20K | B9: 6 | C9: 14000 | D9: 3500 | E9: 294000000
A10: 20K-50K | B10: 6 | C10: 31000 | D10: 4200 | E10: 781200000
A11: 50K-100K | B11: 2 | C11: 70000 | D11: 4800 | E11: 672000000
A12: 100K+ | B12: 2 | C12: 220000 | D12: 7000 | E12: 3080000000
A13: Municipalities subtotal | B13: 57 | E13: 5106350000
A15: Counties / Parishes
A16: <1K | B16: 0 | C16: 450 | D16: 3500 | E16: 0
A17: 1K-5K | B17: 0 | C17: 2700 | D17: 3300 | E17: 0
A18: 5K-10K | B18: 0 | C18: 7100 | D18: 2900 | E18: 0
A19: 10K-20K | B19: 0 | C19: 14000 | D19: 2700 | E19: 0
A20: 20K-50K | B20: 1 | C20: 31000 | D20: 2900 | E20: 89900000
A21: 50K-100K | B21: 1 | C21: 70000 | D21: 3200 | E21: 224000000
A22: GRAND TOTAL | B22: =B13+B23+B27 | C22: 220000 | D22: 3500 | E22: =E13+E23+E27
A23: Counties / Parishes subtotal | B23: =SUM(B16:B22) | E23: =SUM(E16:E22)
A25: Special Districts
A26: (all sizes) | B26: 256 | D26: 7600000 | E26: 1945600000
A27: Special Districts subtotal | B27: 256 | E27: 1945600000

Sheet FL
A1: FL — Florida
A2: Counts and estimated annual operating spend by entity type and bucket.
A4: Entity / Bucket | B4: Count | C4: Avg Pop | D4: $/capita | E4: Spend ($)
A5: Municipalities
A6: <1K | B6: 95 | C6: 450 | D6: 2000 | E6: 85500000
A7: 1K-5K | B7: 104 | C7: 2700 | D7: 2500 | E7: 702000000
A8: 5K-10K | B8: 53 | C8: 7100 | D8: 3000 | E8: 1128900000
A9: 10K-20K | B9: 54 | C9: 14000 | D9: 3500 | E9: 2646000000
A10: 20K-50K | B10: 57 | C10: 31000 | D10: 4200 | E10: 7421400000
A11: 50K-100K | B11: 27 | C11: 70000 | D11: 4800 | E11: 9072000000
A12: 100K+ | B12: 22 | C12: 220000 | D12: 7000 | E12: 33880000000
A13: Municipalities subtotal | B13: 412 | E13: 54935800000
A15: Counties / Parishes
A16: <1K | B16: 0 | C16: 450 | D16: 3500 | E16: 0
A17: 1K-5K | B17: 3 | C17: 2700 | D17: 3300 | E17: 26730000
A18: 5K-10K | B18: 4 | C18: 7100 | D18: 2900 | E18: 82360000
A19: 10K-20K | B19: 8 | C19: 14000 | D19: 2700 | E19: 302400000
A20: 20K-50K | B20: 17 | C20: 31000 | D20: 2900 | E20: 1528300000
A21: 50K-100K | B21: 14 | C21: 70000 | D21: 3200 | E21: 3136000000
A22: GRAND TOTAL | B22: =B13+B23+B27 | C22: 220000 | D22: 3500 | E22: =E13+E23+E27
A23: Counties / Parishes subtotal | B23: =SUM(B16:B22) | E23: =SUM(E16:E22)
A25: Special Districts
A26: (all sizes) | B26: 1134 | D26: 7600000 | E26: 8618400000
A27: Special Districts subtotal | B27: 1134 | E27: 8618400000

Sheet GA
A1: GA — Georgia
A2: Counts and estimated annual operating spend by entity type and bucket.
A4: Entity / Bucket | B4: Count | C4: Avg Pop | D4: $/capita | E4: Spend ($)
A5: Municipalities
A6: <1K | B6: 188 | C6: 450 | D6: 2000 | E6: 169200000
A7: 1K-5K | B7: 161 | C7: 2700 | D7: 2500 | E7: 1086750000
A8: 5K-10K | B8: 64 | C8: 7100 | D8: 3000 | E8: 1363200000
A9: 10K-20K | B9: 54 | C9: 14000 | D9: 3500 | E9: 2646000000
A10: 20K-50K | B10: 43 | C10: 31000 | D10: 4200 | E10: 5598600000
A11: 50K-100K | B11: 16 | C11: 70000 | D11: 4800 | E11: 5376000000
A12: 100K+ | B12: 11 | C12: 220000 | D12: 7000 | E12: 16940000000
A13: Municipalities subtotal | B13: 537 | E13: 33179750000
A15: Counties / Parishes
A16: <1K | B16: 1 | C16: 450 | D16: 3500 | E16: 1575000
A17: 1K-5K | B17: 12 | C17: 2700 | D17: 3300 | E17: 106920000
A18: 5K-10K | B18: 17 | C18: 7100 | D18: 2900 | E18: 350030000
A19: 10K-20K | B19: 26 | C19: 14000 | D19: 2700 | E19: 982800000
A20: 20K-50K | B20: 40 | C20: 31000 | D20: 2900 | E20: 3596000000
A21: 50K-100K | B21: 26 | C21: 70000 | D21: 3200 | E21: 5824000000
A22: GRAND TOTAL | B22: =B13+B23+B27 | C22: 220000 | D22: 3500 | E22: =E13+E23+E27
A23: Counties / Parishes subtotal | B23: =SUM(B16:B22) | E23: =SUM(E16:E22)
A25: Special Districts
A26: (all sizes) | B26: 720 | D26: 7600000 | E26: 5472000000
A27: Special Districts subtotal | B27: 720 | E27: 5472000000

Sheet HI
A1: HI — Hawaii
A2: Counts and estimated annual operating spend by entity type and bucket.
A4: Entity / Bucket | B4: Count | C4: Avg Pop | D4: $/capita | E4: Spend ($)
A5: Municipalities
A6: <1K | B6: 1 | C6: 450 | D6: 2000 | E6: 900000
A7: 1K-5K | B7: 0 | C7: 2700 | D7: 2500 | E7: 0
A8: 5K-10K | B8: 0 | C8: 7100 | D8: 3000 | E8: 0
A9: 10K-20K | B9: 0 | C9: 14000 | D9: 3500 | E9: 0
A10: 20K-50K | B10: 0 | C10: 31000 | D10: 4200 | E10: 0
A11: 50K-100K | B11: 0 | C11: 70000 | D11: 4800 | E11: 0
A12: 100K+ | B12: 0 | C12: 220000 | D12: 7000 | E12: 0
A13: Municipalities subtotal | B13: 1 | E13: 900000
A15: Counties / Parishes
A16: <1K | B16: 0 | C16: 450 | D16: 3500 | E16: 0
A17: 1K-5K | B17: 0 | C17: 2700 | D17: 3300 | E17: 0
A18: 5K-10K | B18: 0 | C18: 7100 | D18: 2900 | E18: 0
A19: 10K-20K | B19: 0 | C19: 14000 | D19: 2700 | E19: 0
A20: 20K-50K | B20: 1 | C20: 31000 | D20: 2900 | E20: 89900000
A21: 50K-100K | B21: 1 | C21: 70000 | D21: 3200 | E21: 224000000
A22: GRAND TOTAL | B22: =B13+B23+B27 | C22: 220000 | D22: 3500 | E22: =E13+E23+E27
A23: Counties / Parishes subtotal | B23: =SUM(B16:B22) | E23: =SUM(E16:E22)
A25: Special Districts
A26: (all sizes) | B26: 17 | D26: 7600000 | E26: 129200000
A27: Special Districts subtotal | B27: 17 | E27: 129200000

Sheet ID
A1: ID — Idaho
A2: Counts and estimated annual operating spend by entity type and bucket.
A4: Entity / Bucket | B4: Count | C4: Avg Pop | D4: $/capita | E4: Spend ($)
A5: Municipalities
A6: <1K | B6: 77 | C6: 450 | D6: 2000 | E6: 69300000
A7: 1K-5K | B7: 63 | C7: 2700 | D7: 2500 | E7: 425250000
A8: 5K-10K | B8: 23 | C8: 7100 | D8: 3000 | E8: 489900000
A9: 10K-20K | B9: 18 | C9: 14000 | D9: 3500 | E9: 882000000
A10: 20K-50K | B10: 13 | C10: 31000 | D10: 4200 | E10: 1692600000
A11: 50K-100K | B11: 4 | C11: 70000 | D11: 4800 | E11: 1344000000
A12: 100K+ | B12: 2 | C12: 220000 | D12: 7000 | E12: 3080000000
A13: Municipalities subtotal | B13: 200 | E13: 7983050000
A15: Counties / Parishes
A16: <1K | B16: 1 | C16: 450 | D16: 3500 | E16: 1575000
A17: 1K-5K | B17: 5 | C17: 2700 | D17: 3300 | E17: 44550000
A18: 5K-10K | B18: 6 | C18: 7100 | D18: 2900 | E18: 123540000
A19: 10K-20K | B19: 8 | C19: 14000 | D19: 2700 | E19: 302400000
A20: 20K-50K | B20: 11 | C20: 31000 | D20: 2900 | E20: 988900000
A21: 50K-100K | B21: 7 | C21: 70000 | D21: 3200 | E21: 1568000000
A22: GRAND TOTAL | B22: =B13+B23+B27 | C22: 220000 | D22: 3500 | E22: =E13+E23+E27
A23: Counties / Parishes subtotal | B23: =SUM(B16:B22) | E23: =SUM(E16:E22)
A25: Special Districts
A26: (all sizes) | B26: 1058 | D26: 7600000 | E26: 8040800000
A27: Special Districts subtotal | B27: 1058 | E27: 8040800000

Sheet IL
A1: IL — Illinois
A2: Counts and estimated annual operating spend by entity type and bucket.
A4: Entity / Bucket | B4: Count | C4: Avg Pop | D4: $/capita | E4: Spend ($)
A5: Municipalities
A6: <1K | B6: 299 | C6: 450 | D6: 2000 | E6: 269100000
A7: 1K-5K | B7: 327 | C7: 2700 | D7: 2500 | E7: 2207250000
A8: 5K-10K | B8: 168 | C8: 7100 | D8: 3000 | E8: 3578400000
A9: 10K-20K | B9: 171 | C9: 14000 | D9: 3500 | E9: 8379000000
A10: 20K-50K | B10: 180 | C10: 31000 | D10: 4200 | E10: 23436000000
A11: 50K-100K | B11: 84 | C11: 70000 | D11: 4800 | E11: 28224000000
A12: 100K+ | B12: 69 | C12: 220000 | D12: 7000 | E12: 106260000000
A13: Municipalities subtotal | B13: 1298 | E13: 172353750000
A15: Counties / Parishes
A16: <1K | B16: 0 | C16: 450 | D16: 3500 | E16: 0
A17: 1K-5K | B17: 4 | C17: 2700 | D17: 3300 | E17: 35640000
A18: 5K-10K | B18: 7 | C18: 7100 | D18: 2900 | E18: 144130000
A19: 10K-20K | B19: 13 | C19: 14000 | D19: 2700 | E19: 491400000
A20: 20K-50K | B20: 26 | C20: 31000 | D20: 2900 | E20: 2337400000
A21: 50K-100K | B21: 21 | C21: 70000 | D21: 3200 | E21: 4704000000
A22: GRAND TOTAL | B22: =B13+B23+B33+B37 | C22: 220000 | D22: 3500 | E22: =E13+E23+E33+E37
A23: Counties / Parishes subtotal | B23: =SUM(B16:B22) | E23: =SUM(E16:E22)
A25: Townships
A26: <1K | B26: 565 | C26: 450 | D26: 600 | E26: 152550000
A27: 1K-5K | B27: 460 | C27: 2700 | D27: 800 | E27: 993600000
A28: 5K-10K | B28: 167 | C28: 7100 | D28: 1100 | E28: 1304270000
A29: 10K-20K | B29: 113 | C29: 14000 | D29: 1400 | E29: 2214800000
A30: 20K-50K | B30: 89 | C30: 31000 | D30: 1600 | E30: 4414400000
A31: 50K-100K | B31: 37 | C31: 70000 | D31: 1700 | E31: 4403000000
A32: 100K+ | B32: 0 | C32: 220000 | D32: 1800 | E32: 0
A33: Townships subtotal | B33: 1431 | E33: 13482620000
A35: Special Districts
A36: (all sizes) | B36: 3050 | D36: 7600000 | E36: 23180000000
A37: Special Districts subtotal | B37: 3050 | E37: 23180000000

Sheet IN
A1: IN — Indiana
A2: Counts and estimated annual operating spend by entity type and bucket.
A4: Entity / Bucket | B4: Count | C4: Avg Pop | D4: $/capita | E4: Spend ($)
A5: Municipalities
A6: <1K | B6: 199 | C6: 450 | D6: 2000 | E6: 179100000
A7: 1K-5K | B7: 170 | C7: 2700 | D7: 2500 | E7: 1147500000
A8: 5K-10K | B8: 68 | C8: 7100 | D8: 3000 | E8: 1448400000
A9: 10K-20K | B9: 57 | C9: 14000 | D9: 3500 | E9: 2793000000
A10: 20K-50K | B10: 46 | C10: 31000 | D10: 4200 | E10: 5989200000
A11: 50K-100K | B11: 17 | C11: 70000 | D11: 4800 | E11: 5712000000
A12: 100K+ | B12: 11 | C12: 220000 | D12: 7000 | E12: 16940000000
A13: Municipalities subtotal | B13: 568 | E13: 34209200000
A15: Counties / Parishes
A16: <1K | B16: 1 | C16: 450 | D16: 3500 | E16: 1575000
A17: 1K-5K | B17: 7 | C17: 2700 | D17: 3300 | E17: 62370000
A18: 5K-10K | B18: 10 | C18: 7100 | D18: 2900 | E18: 205900000
A19: 10K-20K | B19: 15 | C19: 14000 | D19: 2700 | E19: 567000000
A20: 20K-50K | B20: 24 | C20: 31000 | D20: 2900 | E20: 2157600000
A21: 50K-100K | B21: 16 | C21: 70000 | D21: 3200 | E21: 3584000000
A22: GRAND TOTAL | B22: =B13+B23+B33+B37 | C22: 220000 | D22: 3500 | E22: =E13+E23+E33+E37
A23: Counties / Parishes subtotal | B23: =SUM(B16:B22) | E23: =SUM(E16:E22)
A25: Townships
A26: <1K | B26: 503 | C26: 450 | D26: 600 | E26: 135810000
A27: 1K-5K | B27: 322 | C27: 2700 | D27: 800 | E27: 695520000
A28: 5K-10K | B28: 91 | C28: 7100 | D28: 1100 | E28: 710710000
A29: 10K-20K | B29: 50 | C29: 14000 | D29: 1400 | E29: 980000000
A30: 20K-50K | B30: 30 | C30: 31000 | D30: 1600 | E30: 1488000000
A31: 50K-100K | B31: 10 | C31: 70000 | D31: 1700 | E31: 1190000000
A32: 100K+ | B32: 0 | C32: 220000 | D32: 1800 | E32: 0
A33: Townships subtotal | B33: 1006 | E33: 5200040000
A35: Special Districts
A36: (all sizes) | B36: 1262 | D36: 7600000 | E36: 9591200000
A37: Special Districts subtotal | B37: 1262 | E37: 9591200000

Sheet IA
A1: IA — Iowa
A2: Counts and estimated annual operating spend by entity type and bucket.
A4: Entity / Bucket | B4: Count | C4: Avg Pop | D4: $/capita | E4: Spend ($)
A5: Municipalities
A6: <1K | B6: 420 | C6: 450 | D6: 2000 | E6: 378000000
A7: 1K-5K | B7: 302 | C7: 2700 | D7: 2500 | E7: 2038500000
A8: 5K-10K | B8: 98 | C8: 7100 | D8: 3000 | E8: 2087400000
A9: 10K-20K | B9: 66 | C9: 14000 | D9: 3500 | E9: 3234000000
A10: 20K-50K | B10: 40 | C10: 31000 | D10: 4200 | E10: 5208000000
A11: 50K-100K | B11: 10 | C11: 70000 | D11: 4800 | E11: 3360000000
A12: 100K+ | B12: 5 | C12: 220000 | D12: 7000 | E12: 7700000000
A13: Municipalities subtotal | B13: 941 | E13: 24005900000
A15: Counties / Parishes
A16: <1K | B16: 2 | C16: 450 | D16: 3500 | E16: 3150000
A17: 1K-5K | B17: 15 | C17: 2700 | D17: 3300 | E17: 133650000
A18: 5K-10K | B18: 17 | C18: 7100 | D18: 2900 | E18: 350030000
A19: 10K-20K | B19: 21 | C19: 14000 | D19: 2700 | E19: 793800000
A20: 20K-50K | B20: 24 | C20: 31000 | D20: 2900 | E20: 2157600000
A21: 50K-100K | B21: 11 | C21: 70000 | D21: 3200 | E21: 2464000000
A22: GRAND TOTAL | B22: =B13+B23+B27 | C22: 220000 | D22: 3500 | E22: =E13+E23+E27
A23: Counties / Parishes subtotal | B23: =SUM(B16:B22) | E23: =SUM(E16:E22)
A25: Special Districts
A26: (all sizes) | B26: 562 | D26: 7600000 | E26: 4271200000
A27: Special Districts subtotal | B27: 562 | E27: 4271200000

Sheet KS
A1: KS — Kansas
A2: Counts and estimated annual operating spend by entity type and bucket.
A4: Entity / Bucket | B4: Count | C4: Avg Pop | D4: $/capita | E4: Spend ($)
A5: Municipalities
A6: <1K | B6: 278 | C6: 450 | D6: 2000 | E6: 250200000
A7: 1K-5K | B7: 200 | C7: 2700 | D7: 2500 | E7: 1350000000
A8: 5K-10K | B8: 65 | C8: 7100 | D8: 3000 | E8: 1384500000
A9: 10K-20K | B9: 44 | C9: 14000 | D9: 3500 | E9: 2156000000
A10: 20K-50K | B10: 27 | C10: 31000 | D10: 4200 | E10: 3515400000
A11: 50K-100K | B11: 7 | C11: 70000 | D11: 4800 | E11: 2352000000
A12: 100K+ | B12: 3 | C12: 220000 | D12: 7000 | E12: 4620000000
A13: Municipalities subtotal | B13: 624 | E13: 15628100000
A15: Counties / Parishes
A16: <1K | B16: 2 | C16: 450 | D16: 3500 | E16: 3150000
A17: 1K-5K | B17: 16 | C17: 2700 | D17: 3300 | E17: 142560000
A18: 5K-10K | B18: 17 | C18: 7100 | D18: 2900 | E18: 350030000
A19: 10K-20K | B19: 22 | C19: 14000 | D19: 2700 | E19: 831600000
A20: 20K-50K | B20: 25 | C20: 31000 | D20: 2900 | E20: 2247500000
A21: 50K-100K | B21: 12 | C21: 70000 | D21: 3200 | E21: 2688000000
A22: GRAND TOTAL | B22: =B13+B23+B33+B37 | C22: 220000 | D22: 3500 | E22: =E13+E23+E33+E37
A23: Counties / Parishes subtotal | B23: =SUM(B16:B22) | E23: =SUM(E16:E22)
A25: Townships
A26: <1K | B26: 727 | C26: 450 | D26: 600 | E26: 196290000
A27: 1K-5K | B27: 390 | C27: 2700 | D27: 800 | E27: 842400000
A28: 5K-10K | B28: 89 | C28: 7100 | D28: 1100 | E28: 695090000
A29: 10K-20K | B29: 40 | C29: 14000 | D29: 1400 | E29: 784000000
A30: 20K-50K | B30: 18 | C30: 31000 | D30: 1600 | E30: 892800000
A31: 50K-100K | B31: 4 | C31: 70000 | D31: 1700 | E31: 476000000
A32: 100K+ | B32: 0 | C32: 220000 | D32: 1800 | E32: 0
A33: Townships subtotal | B33: 1268 | E33: 3886580000
A35: Special Districts
A36: (all sizes) | B36: 1535 | D36: 7600000 | E36: 11666000000
A37: Special Districts subtotal | B37: 1535 | E37: 11666000000

Sheet KY
A1: KY — Kentucky
A2: Counts and estimated annual operating spend by entity type and bucket.
A4: Entity / Bucket | B4: Count | C4: Avg Pop | D4: $/capita | E4: Spend ($)
A5: Municipalities
A6: <1K | B6: 161 | C6: 450 | D6: 2000 | E6: 144900000
A7: 1K-5K | B7: 133 | C7: 2700 | D7: 2500 | E7: 897750000
A8: 5K-10K | B8: 48 | C8: 7100 | D8: 3000 | E8: 1022400000
A9: 10K-20K | B9: 36 | C9: 14000 | D9: 3500 | E9: 1764000000
A10: 20K-50K | B10: 26 | C10: 31000 | D10: 4200 | E10: 3385200000
A11: 50K-100K | B11: 9 | C11: 70000 | D11: 4800 | E11: 3024000000
A12: 100K+ | B12: 5 | C12: 220000 | D12: 7000 | E12: 7700000000
A13: Municipalities subtotal | B13: 418 | E13: 17938250000
A15: Counties / Parishes
A16: <1K | B16: 1 | C16: 450 | D16: 3500 | E16: 1575000
A17: 1K-5K | B17: 13 | C17: 2700 | D17: 3300 | E17: 115830000
A18: 5K-10K | B18: 16 | C18: 7100 | D18: 2900 | E18: 329440000
A19: 10K-20K | B19: 22 | C19: 14000 | D19: 2700 | E19: 831600000
A20: 20K-50K | B20: 31 | C20: 31000 | D20: 2900 | E20: 2786900000
A21: 50K-100K | B21: 18 | C21: 70000 | D21: 3200 | E21: 4032000000
A22: GRAND TOTAL | B22: =B13+B23+B27 | C22: 220000 | D22: 3500 | E22: =E13+E23+E27
A23: Counties / Parishes subtotal | B23: =SUM(B16:B22) | E23: =SUM(E16:E22)
A25: Special Districts
A26: (all sizes) | B26: 720 | D26: 7600000 | E26: 5472000000
A27: Special Districts subtotal | B27: 720 | E27: 5472000000

Sheet LA
A1: LA — Louisiana
A2: Counts and estimated annual operating spend by entity type and bucket.
A4: Entity / Bucket | B4: Count | C4: Avg Pop | D4: $/capita | E4: Spend ($)
A5: Municipalities
A6: <1K | B6: 117 | C6: 450 | D6: 2000 | E6: 105300000
A7: 1K-5K | B7: 97 | C7: 2700 | D7: 2500 | E7: 654750000
A8: 5K-10K | B8: 35 | C8: 7100 | D8: 3000 | E8: 745500000
A9: 10K-20K | B9: 27 | C9: 14000 | D9: 3500 | E9: 1323000000
A10: 20K-50K | B10: 19 | C10: 31000 | D10: 4200 | E10: 2473800000
A11: 50K-100K | B11: 6 | C11: 70000 | D11: 4800 | E11: 2016000000
A12: 100K+ | B12: 3 | C12: 220000 | D12: 7000 | E12: 4620000000
A13: Municipalities subtotal | B13: 304 | E13: 11938350000
A15: Counties / Parishes
A16: <1K | B16: 1 | C16: 450 | D16: 3500 | E16: 1575000
A17: 1K-5K | B17: 7 | C17: 2700 | D17: 3300 | E17: 62370000
A18: 5K-10K | B18: 8 | C18: 7100 | D18: 2900 | E18: 164720000
A19: 10K-20K | B19: 11 | C19: 14000 | D19: 2700 | E19: 415800000
A20: 20K-50K | B20: 16 | C20: 31000 | D20: 2900 | E20: 1438400000
A21: 50K-100K | B21: 9 | C21: 70000 | D21: 3200 | E21: 2016000000
A22: GRAND TOTAL | B22: =B13+B23+B27 | C22: 220000 | D22: 3500 | E22: =E13+E23+E27
A23: Counties / Parishes subtotal | B23: =SUM(B16:B22) | E23: =SUM(E16:E22)
A25: Special Districts
A26: (all sizes) | B26: 95 | D26: 7600000 | E26: 722000000
A27: Special Districts subtotal | B27: 95 | E27: 722000000

Sheet ME
A1: ME — Maine
A2: Counts and estimated annual operating spend by entity type and bucket.
A4: Entity / Bucket | B4: Count | C4: Avg Pop | D4: $/capita | E4: Spend ($)
A5: Municipalities
A6: <1K | B6: 10 | C6: 450 | D6: 2000 | E6: 9000000
A7: 1K-5K | B7: 7 | C7: 2700 | D7: 2500 | E7: 47250000
A8: 5K-10K | B8: 2 | C8: 7100 | D8: 3000 | E8: 42600000
A9: 10K-20K | B9: 2 | C9: 14000 | D9: 3500 | E9: 98000000
A10: 20K-50K | B10: 1 | C10: 31000 | D10: 4200 | E10: 130200000
A11: 50K-100K | B11: 0 | C11: 70000 | D11: 4800 | E11: 0
A12: 100K+ | B12: 0 | C12: 220000 | D12: 7000 | E12: 0
A13: Municipalities subtotal | B13: 22 | E13: 327050000
A15: Counties / Parishes
A16: <1K | B16: 0 | C16: 450 | D16: 3500 | E16: 0
A17: 1K-5K | B17: 3 | C17: 2700 | D17: 3300 | E17: 26730000
A18: 5K-10K | B18: 3 | C18: 7100 | D18: 2900 | E18: 61770000
A19: 10K-20K | B19: 3 | C19: 14000 | D19: 2700 | E19: 113400000
A20: 20K-50K | B20: 4 | C20: 31000 | D20: 2900 | E20: 359600000
A21: 50K-100K | B21: 2 | C21: 70000 | D21: 3200 | E21: 448000000
A22: GRAND TOTAL | B22: =B13+B23+B33+B37 | C22: 220000 | D22: 3500 | E22: =E13+E23+E33+E37
A23: Counties / Parishes subtotal | B23: =SUM(B16:B22) | E23: =SUM(E16:E22)
A25: Townships
A26: <1K | B26: 268 | C26: 450 | D26: 600 | E26: 72360000
A27: 1K-5K | B27: 144 | C27: 2700 | D27: 800 | E27: 311040000
A28: 5K-10K | B28: 32 | C28: 7100 | D28: 1100 | E28: 249920000
A29: 10K-20K | B29: 15 | C29: 14000 | D29: 1400 | E29: 294000000
A30: 20K-50K | B30: 7 | C30: 31000 | D30: 1600 | E30: 347200000
A31: 50K-100K | B31: 1 | C31: 70000 | D31: 1700 | E31: 119000000
A32: 100K+ | B32: 0 | C32: 220000 | D32: 1800 | E32: 0
A33: Townships subtotal | B33: 467 | E33: 1393520000
A35: Special Districts
A36: (all sizes) | B36: 226 | D36: 7600000 | E36: 1717600000
A37: Special Districts subtotal | B37: 226 | E37: 1717600000

Sheet MD
A1: MD — Maryland
A2: Counts and estimated annual operating spend by entity type and bucket.
A4: Entity / Bucket | B4: Count | C4: Avg Pop | D4: $/capita | E4: Spend ($)
A5: Municipalities
A6: <1K | B6: 47 | C6: 450 | D6: 2000 | E6: 42300000
A7: 1K-5K | B7: 45 | C7: 2700 | D7: 2500 | E7: 303750000
A8: 5K-10K | B8: 20 | C8: 7100 | D8: 3000 | E8: 426000000
A9: 10K-20K | B9: 18 | C9: 14000 | D9: 3500 | E9: 882000000
A10: 20K-50K | B10: 16 | C10: 31000 | D10: 4200 | E10: 2083200000
A11: 50K-100K | B11: 6 | C11: 70000 | D11: 4800 | E11: 2016000000
A12: 100K+ | B12: 5 | C12: 220000 | D12: 7000 | E12: 7700000000
A13: Municipalities subtotal | B13: 157 | E13: 13453250000
A15: Counties / Parishes
A16: <1K | B16: 0 | C16: 450 | D16: 3500 | E16: 0
A17: 1K-5K | B17: 1 | C17: 2700 | D17: 3300 | E17: 8910000
A18: 5K-10K | B18: 2 | C18: 7100 | D18: 2900 | E18: 41180000
A19: 10K-20K | B19: 4 | C19: 14000 | D19: 2700 | E19: 151200000
A20: 20K-50K | B20: 6 | C20: 31000 | D20: 2900 | E20: 539400000
A21: 50K-100K | B21: 4 | C21: 70000 | D21: 3200 | E21: 896000000
A22: GRAND TOTAL | B22: =B13+B23+B27 | C22: 220000 | D22: 3500 | E22: =E13+E23+E27
A23: Counties / Parishes subtotal | B23: =SUM(B16:B22) | E23: =SUM(E16:E22)
A25: Special Districts
A26: (all sizes) | B26: 90 | D26: 7600000 | E26: 684000000
A27: Special Districts subtotal | B27: 90 | E27: 684000000

Sheet MA
A1: MA — Massachusetts
A2: Counts and estimated annual operating spend by entity type and bucket.
A4: Entity / Bucket | B4: Count | C4: Avg Pop | D4: $/capita | E4: Spend ($)
A5: Municipalities
A6: <1K | B6: 12 | C6: 450 | D6: 2000 | E6: 10800000
A7: 1K-5K | B7: 13 | C7: 2700 | D7: 2500 | E7: 87750000
A8: 5K-10K | B8: 7 | C8: 7100 | D8: 3000 | E8: 149100000
A9: 10K-20K | B9: 7 | C9: 14000 | D9: 3500 | E9: 343000000
A10: 20K-50K | B10: 7 | C10: 31000 | D10: 4200 | E10: 911400000
A11: 50K-100K | B11: 4 | C11: 70000 | D11: 4800 | E11: 1344000000
A12: 100K+ | B12: 3 | C12: 220000 | D12: 7000 | E12: 4620000000
A13: Municipalities subtotal | B13: 53 | E13: 7466050000
A15: Counties / Parishes
A16: <1K | B16: 0 | C16: 450 | D16: 3500 | E16: 0
A17: 1K-5K | B17: 0 | C17: 2700 | D17: 3300 | E17: 0
A18: 5K-10K | B18: 0 | C18: 7100 | D18: 2900 | E18: 0
A19: 10K-20K | B19: 1 | C19: 14000 | D19: 2700 | E19: 37800000
A20: 20K-50K | B20: 1 | C20: 31000 | D20: 2900 | E20: 89900000
A21: 50K-100K | B21: 1 | C21: 70000 | D21: 3200 | E21: 224000000
A22: GRAND TOTAL | B22: =B13+B23+B33+B37 | C22: 220000 | D22: 3500 | E22: =E13+E23+E33+E37
A23: Counties / Parishes subtotal | B23: =SUM(B16:B22) | E23: =SUM(E16:E22)
A25: Townships
A26: <1K | B26: 118 | C26: 450 | D26: 600 | E26: 31860000
A27: 1K-5K | B27: 96 | C27: 2700 | D27: 800 | E27: 207360000
A28: 5K-10K | B28: 35 | C28: 7100 | D28: 1100 | E28: 273350000
A29: 10K-20K | B29: 23 | C29: 14000 | D29: 1400 | E29: 450800000
A30: 20K-50K | B30: 18 | C30: 31000 | D30: 1600 | E30: 892800000
A31: 50K-100K | B31: 8 | C31: 70000 | D31: 1700 | E31: 952000000
A32: 100K+ | B32: 0 | C32: 220000 | D32: 1800 | E32: 0
A33: Townships subtotal | B33: 298 | E33: 2808170000
A35: Special Districts
A36: (all sizes) | B36: 480 | D36: 7600000 | E36: 3648000000
A37: Special Districts subtotal | B37: 480 | E37: 3648000000

Sheet MI
A1: MI — Michigan
A2: Counts and estimated annual operating spend by entity type and bucket.
A4: Entity / Bucket | B4: Count | C4: Avg Pop | D4: $/capita | E4: Spend ($)
A5: Municipalities
A6: <1K | B6: 186 | C6: 450 | D6: 2000 | E6: 167400000
A7: 1K-5K | B7: 160 | C7: 2700 | D7: 2500 | E7: 1080000000
A8: 5K-10K | B8: 64 | C8: 7100 | D8: 3000 | E8: 1363200000
A9: 10K-20K | B9: 53 | C9: 14000 | D9: 3500 | E9: 2597000000
A10: 20K-50K | B10: 43 | C10: 31000 | D10: 4200 | E10: 5598600000
A11: 50K-100K | B11: 16 | C11: 70000 | D11: 4800 | E11: 5376000000
A12: 100K+ | B12: 11 | C12: 220000 | D12: 7000 | E12: 16940000000
A13: Municipalities subtotal | B13: 533 | E13: 33122200000
A15: Counties / Parishes
A16: <1K | B16: 1 | C16: 450 | D16: 3500 | E16: 1575000
A17: 1K-5K | B17: 7 | C17: 2700 | D17: 3300 | E17: 62370000
A18: 5K-10K | B18: 9 | C18: 7100 | D18: 2900 | E18: 185310000
A19: 10K-20K | B19: 14 | C19: 14000 | D19: 2700 | E19: 529200000
A20: 20K-50K | B20: 21 | C20: 31000 | D20: 2900 | E20: 1887900000
A21: 50K-100K | B21: 14 | C21: 70000 | D21: 3200 | E21: 3136000000
A22: GRAND TOTAL | B22: =B13+B23+B33+B37 | C22: 220000 | D22: 3500 | E22: =E13+E23+E33+E37
A23: Counties / Parishes subtotal | B23: =SUM(B16:B22) | E23: =SUM(E16:E22)
A25: Townships
A26: <1K | B26: 620 | C26: 450 | D26: 600 | E26: 167400000
A27: 1K-5K | B27: 397 | C27: 2700 | D27: 800 | E27: 857520000
A28: 5K-10K | B28: 112 | C28: 7100 | D28: 1100 | E28: 874720000
A29: 10K-20K | B29: 62 | C29: 14000 | D29: 1400 | E29: 1215200000
A30: 20K-50K | B30: 37 | C30: 31000 | D30: 1600 | E30: 1835200000
A31: 50K-100K | B31: 12 | C31: 70000 | D31: 1700 | E31: 1428000000
A32: 100K+ | B32: 0 | C32: 220000 | D32: 1800 | E32: 0
A33: Townships subtotal | B33: 1240 | E33: 6378040000
A35: Special Districts
A36: (all sizes) | B36: 451 | D36: 7600000 | E36: 3427600000
A37: Special Districts subtotal | B37: 451 | E37: 3427600000

Sheet MN
A1: MN — Minnesota
A2: Counts and estimated annual operating spend by entity type and bucket.
A4: Entity / Bucket | B4: Count | C4: Avg Pop | D4: $/capita | E4: Spend ($)
A5: Municipalities
A6: <1K | B6: 299 | C6: 450 | D6: 2000 | E6: 269100000
A7: 1K-5K | B7: 256 | C7: 2700 | D7: 2500 | E7: 1728000000
A8: 5K-10K | B8: 102 | C8: 7100 | D8: 3000 | E8: 2172600000
A9: 10K-20K | B9: 85 | C9: 14000 | D9: 3500 | E9: 4165000000
A10: 20K-50K | B10: 68 | C10: 31000 | D10: 4200 | E10: 8853600000
A11: 50K-100K | B11: 26 | C11: 70000 | D11: 4800 | E11: 8736000000
A12: 100K+ | B12: 17 | C12: 220000 | D12: 7000 | E12: 26180000000
A13: Municipalities subtotal | B13: 853 | E13: 52104300000
A15: Counties / Parishes
A16: <1K | B16: 1 | C16: 450 | D16: 3500 | E16: 1575000
A17: 1K-5K | B17: 7 | C17: 2700 | D17: 3300 | E17: 62370000
A18: 5K-10K | B18: 9 | C18: 7100 | D18: 2900 | E18: 185310000
A19: 10K-20K | B19: 15 | C19: 14000 | D19: 2700 | E19: 567000000
A20: 20K-50K | B20: 23 | C20: 31000 | D20: 2900 | E20: 2067700000
A21: 50K-100K | B21: 15 | C21: 70000 | D21: 3200 | E21: 3360000000
A22: GRAND TOTAL | B22: =B13+B23+B33+B37 | C22: 220000 | D22: 3500 | E22: =E13+E23+E33+E37
A23: Counties / Parishes subtotal | B23: =SUM(B16:B22) | E23: =SUM(E16:E22)
A25: Townships
A26: <1K | B26: 891 | C26: 450 | D26: 600 | E26: 240570000
A27: 1K-5K | B27: 570 | C27: 2700 | D27: 800 | E27: 1231200000
A28: 5K-10K | B28: 160 | C28: 7100 | D28: 1100 | E28: 1249600000
A29: 10K-20K | B29: 89 | C29: 14000 | D29: 1400 | E29: 1744400000
A30: 20K-50K | B30: 53 | C30: 31000 | D30: 1600 | E30: 2628800000
A31: 50K-100K | B31: 18 | C31: 70000 | D31: 1700 | E31: 2142000000
A32: 100K+ | B32: 0 | C32: 220000 | D32: 1800 | E32: 0
A33: Townships subtotal | B33: 1781 | E33: 9236570000
A35: Special Districts
A36: (all sizes) | B36: 482 | D36: 7600000 | E36: 3663200000
A37: Special Districts subtotal | B37: 482 | E37: 3663200000

Sheet MS
A1: MS — Mississippi
A2: Counts and estimated annual operating spend by entity type and bucket.
A4: Entity / Bucket | B4: Count | C4: Avg Pop | D4: $/capita | E4: Spend ($)
A5: Municipalities
A6: <1K | B6: 115 | C6: 450 | D6: 2000 | E6: 103500000
A7: 1K-5K | B7: 94 | C7: 2700 | D7: 2500 | E7: 634500000
A8: 5K-10K | B8: 34 | C8: 7100 | D8: 3000 | E8: 724200000
A9: 10K-20K | B9: 26 | C9: 14000 | D9: 3500 | E9: 1274000000
A10: 20K-50K | B10: 19 | C10: 31000 | D10: 4200 | E10: 2473800000
A11: 50K-100K | B11: 6 | C11: 70000 | D11: 4800 | E11: 2016000000
A12: 100K+ | B12: 3 | C12: 220000 | D12: 7000 | E12: 4620000000
A13: Municipalities subtotal | B13: 297 | E13: 11846000000
A15: Counties / Parishes
A16: <1K | B16: 1 | C16: 450 | D16: 3500 | E16: 1575000
A17: 1K-5K | B17: 9 | C17: 2700 | D17: 3300 | E17: 80190000
A18: 5K-10K | B18: 11 | C18: 7100 | D18: 2900 | E18: 226490000
A19: 10K-20K | B19: 16 | C19: 14000 | D19: 2700 | E19: 604800000
A20: 20K-50K | B20: 21 | C20: 31000 | D20: 2900 | E20: 1887900000
A21: 50K-100K | B21: 12 | C21: 70000 | D21: 3200 | E21: 2688000000
A22: GRAND TOTAL | B22: =B13+B23+B27 | C22: 220000 | D22: 3500 | E22: =E13+E23+E27
A23: Counties / Parishes subtotal | B23: =SUM(B16:B22) | E23: =SUM(E16:E22)
A25: Special Districts
A26: (all sizes) | B26: 467 | D26: 7600000 | E26: 3549200000
A27: Special Districts subtotal | B27: 467 | E27: 3549200000

Sheet MO
A1: MO — Missouri
A2: Counts and estimated annual operating spend by entity type and bucket.
A4: Entity / Bucket | B4: Count | C4: Avg Pop | D4: $/capita | E4: Spend ($)
A5: Municipalities
A6: <1K | B6: 334 | C6: 450 | D6: 2000 | E6: 300600000
A7: 1K-5K | B7: 286 | C7: 2700 | D7: 2500 | E7: 1930500000
A8: 5K-10K | B8: 115 | C8: 7100 | D8: 3000 | E8: 2449500000
A9: 10K-20K | B9: 95 | C9: 14000 | D9: 3500 | E9: 4655000000
A10: 20K-50K | B10: 76 | C10: 31000 | D10: 4200 | E10: 9895200000
A11: 50K-100K | B11: 29 | C11: 70000 | D11: 4800 | E11: 9744000000
A12: 100K+ | B12: 19 | C12: 220000 | D12: 7000 | E12: 29260000000
A13: Municipalities subtotal | B13: 954 | E13: 58234800000
A15: Counties / Parishes
A16: <1K | B16: 1 | C16: 450 | D16: 3500 | E16: 1575000
A17: 1K-5K | B17: 9 | C17: 2700 | D17: 3300 | E17: 80190000
A18: 5K-10K | B18: 13 | C18: 7100 | D18: 2900 | E18: 267670000
A19: 10K-20K | B19: 19 | C19: 14000 | D19: 2700 | E19: 718200000
A20: 20K-50K | B20: 30 | C20: 31000 | D20: 2900 | E20: 2697000000
A21: 50K-100K | B21: 19 | C21: 70000 | D21: 3200 | E21: 4256000000
A22: GRAND TOTAL | B22: =B13+B23+B33+B37 | C22: 220000 | D22: 3500 | E22: =E13+E23+E33+E37
A23: Counties / Parishes subtotal | B23: =SUM(B16:B22) | E23: =SUM(E16:E22)
A25: Townships
A26: <1K | B26: 156 | C26: 450 | D26: 600 | E26: 42120000
A27: 1K-5K | B27: 100 | C27: 2700 | D27: 800 | E27: 216000000
A28: 5K-10K | B28: 28 | C28: 7100 | D28: 1100 | E28: 218680000
A29: 10K-20K | B29: 16 | C29: 14000 | D29: 1400 | E29: 313600000
A30: 20K-50K | B30: 9 | C30: 31000 | D30: 1600 | E30: 446400000
A31: 50K-100K | B31: 3 | C31: 70000 | D31: 1700 | E31: 357000000
A32: 100K+ | B32: 0 | C32: 220000 | D32: 1800 | E32: 0
A33: Townships subtotal | B33: 312 | E33: 1593800000
A35: Special Districts
A36: (all sizes) | B36: 1620 | D36: 7600000 | E36: 12312000000
A37: Special Districts subtotal | B37: 1620 | E37: 12312000000

Sheet MT
A1: MT — Montana
A2: Counts and estimated annual operating spend by entity type and bucket.
A4: Entity / Bucket | B4: Count | C4: Avg Pop | D4: $/capita | E4: Spend ($)
A5: Municipalities
A6: <1K | B6: 57 | C6: 450 | D6: 2000 | E6: 51300000
A7: 1K-5K | B7: 41 | C7: 2700 | D7: 2500 | E7: 276750000
A8: 5K-10K | B8: 13 | C8: 7100 | D8: 3000 | E8: 276900000
A9: 10K-20K | B9: 9 | C9: 14000 | D9: 3500 | E9: 441000000
A10: 20K-50K | B10: 5 | C10: 31000 | D10: 4200 | E10: 651000000
A11: 50K-100K | B11: 1 | C11: 70000 | D11: 4800 | E11: 336000000
A12: 100K+ | B12: 1 | C12: 220000 | D12: 7000 | E12: 1540000000
A13: Municipalities subtotal | B13: 127 | E13: 3572950000
A15: Counties / Parishes
A16: <1K | B16: 1 | C16: 450 | D16: 3500 | E16: 1575000
A17: 1K-5K | B17: 8 | C17: 2700 | D17: 3300 | E17: 71280000
A18: 5K-10K | B18: 9 | C18: 7100 | D18: 2900 | E18: 185310000
A19: 10K-20K | B19: 12 | C19: 14000 | D19: 2700 | E19: 453600000
A20: 20K-50K | B20: 13 | C20: 31000 | D20: 2900 | E20: 1168700000
A21: 50K-100K | B21: 6 | C21: 70000 | D21: 3200 | E21: 1344000000
A22: GRAND TOTAL | B22: =B13+B23+B27 | C22: 220000 | D22: 3500 | E22: =E13+E23+E27
A23: Counties / Parishes subtotal | B23: =SUM(B16:B22) | E23: =SUM(E16:E22)
A25: Special Districts
A26: (all sizes) | B26: 813 | D26: 7600000 | E26: 6178800000
A27: Special Districts subtotal | B27: 813 | E27: 6178800000

Sheet NE
A1: NE — Nebraska
A2: Counts and estimated annual operating spend by entity type and bucket.
A4: Entity / Bucket | B4: Count | C4: Avg Pop | D4: $/capita | E4: Spend ($)
A5: Municipalities
A6: <1K | B6: 237 | C6: 450 | D6: 2000 | E6: 213300000
A7: 1K-5K | B7: 170 | C7: 2700 | D7: 2500 | E7: 1147500000
A8: 5K-10K | B8: 55 | C8: 7100 | D8: 3000 | E8: 1171500000
A9: 10K-20K | B9: 37 | C9: 14000 | D9: 3500 | E9: 1813000000
A10: 20K-50K | B10: 23 | C10: 31000 | D10: 4200 | E10: 2994600000
A11: 50K-100K | B11: 6 | C11: 70000 | D11: 4800 | E11: 2016000000
A12: 100K+ | B12: 2 | C12: 220000 | D12: 7000 | E12: 3080000000
A13: Municipalities subtotal | B13: 530 | E13: 12435900000
A15: Counties / Parishes
A16: <1K | B16: 2 | C16: 450 | D16: 3500 | E16: 3150000
A17: 1K-5K | B17: 14 | C17: 2700 | D17: 3300 | E17: 124740000
A18: 5K-10K | B18: 16 | C18: 7100 | D18: 2900 | E18: 329440000
A19: 10K-20K | B19: 20 | C19: 14000 | D19: 2700 | E19: 756000000
A20: 20K-50K | B20: 23 | C20: 31000 | D20: 2900 | E20: 2067700000
A21: 50K-100K | B21: 10 | C21: 70000 | D21: 3200 | E21: 2240000000
A22: GRAND TOTAL | B22: =B13+B23+B33+B37 | C22: 220000 | D22: 3500 | E22: =E13+E23+E33+E37
A23: Counties / Parishes subtotal | B23: =SUM(B16:B22) | E23: =SUM(E16:E22)
A25: Townships
A26: <1K | B26: 238 | C26: 450 | D26: 600 | E26: 64260000
A27: 1K-5K | B27: 128 | C27: 2700 | D27: 800 | E27: 276480000
A28: 5K-10K | B28: 29 | C28: 7100 | D28: 1100 | E28: 226490000
A29: 10K-20K | B29: 13 | C29: 14000 | D29: 1400 | E29: 254800000
A30: 20K-50K | B30: 6 | C30: 31000 | D30: 1600 | E30: 297600000
A31: 50K-100K | B31: 1 | C31: 70000 | D31: 1700 | E31: 119000000
A32: 100K+ | B32: 0 | C32: 220000 | D32: 1800 | E32: 0
A33: Townships subtotal | B33: 415 | E33: 1238630000
A35: Special Districts
A36: (all sizes) | B36: 1300 | D36: 7600000 | E36: 9880000000
A37: Special Districts subtotal | B37: 1300 | E37: 9880000000

Sheet NV
A1: NV — Nevada
A2: Counts and estimated annual operating spend by entity type and bucket.
A4: Entity / Bucket | B4: Count | C4: Avg Pop | D4: $/capita | E4: Spend ($)
A5: Municipalities
A6: <1K | B6: 6 | C6: 450 | D6: 2000 | E6: 5400000
A7: 1K-5K | B7: 5 | C7: 2700 | D7: 2500 | E7: 33750000
A8: 5K-10K | B8: 2 | C8: 7100 | D8: 3000 | E8: 42600000
A9: 10K-20K | B9: 2 | C9: 14000 | D9: 3500 | E9: 98000000
A10: 20K-50K | B10: 2 | C10: 31000 | D10: 4200 | E10: 260400000
A11: 50K-100K | B11: 1 | C11: 70000 | D11: 4800 | E11: 336000000
A12: 100K+ | B12: 1 | C12: 220000 | D12: 7000 | E12: 1540000000
A13: Municipalities subtotal | B13: 19 | E13: 2316150000
A15: Counties / Parishes
A16: <1K | B16: 0 | C16: 450 | D16: 3500 | E16: 0
A17: 1K-5K | B17: 1 | C17: 2700 | D17: 3300 | E17: 8910000
A18: 5K-10K | B18: 2 | C18: 7100 | D18: 2900 | E18: 41180000
A19: 10K-20K | B19: 2 | C19: 14000 | D19: 2700 | E19: 75600000
A20: 20K-50K | B20: 4 | C20: 31000 | D20: 2900 | E20: 359600000
A21: 50K-100K | B21: 3 | C21: 70000 | D21: 3200 | E21: 672000000
A22: GRAND TOTAL | B22: =B13+B23+B27 | C22: 220000 | D22: 3500 | E22: =E13+E23+E27
A23: Counties / Parishes subtotal | B23: =SUM(B16:B22) | E23: =SUM(E16:E22)
A25: Special Districts
A26: (all sizes) | B26: 175 | D26: 7600000 | E26: 1330000000
A27: Special Districts subtotal | B27: 175 | E27: 1330000000

Sheet NH
A1: NH — New Hampshire
A2: Counts and estimated annual operating spend by entity type and bucket.
A4: Entity / Bucket | B4: Count | C4: Avg Pop | D4: $/capita | E4: Spend ($)
A5: Municipalities
A6: <1K | B6: 5 | C6: 450 | D6: 2000 | E6: 4500000
A7: 1K-5K | B7: 4 | C7: 2700 | D7: 2500 | E7: 27000000
A8: 5K-10K | B8: 2 | C8: 7100 | D8: 3000 | E8: 42600000
A9: 10K-20K | B9: 1 | C9: 14000 | D9: 3500 | E9: 49000000
A10: 20K-50K | B10: 1 | C10: 31000 | D10: 4200 | E10: 130200000
A11: 50K-100K | B11: 0 | C11: 70000 | D11: 4800 | E11: 0
A12: 100K+ | B12: 0 | C12: 220000 | D12: 7000 | E12: 0
A13: Municipalities subtotal | B13: 13 | E13: 253300000
A15: Counties / Parishes
A16: <1K | B16: 0 | C16: 450 | D16: 3500 | E16: 0
A17: 1K-5K | B17: 1 | C17: 2700 | D17: 3300 | E17: 8910000
A18: 5K-10K | B18: 1 | C18: 7100 | D18: 2900 | E18: 20590000
A19: 10K-20K | B19: 2 | C19: 14000 | D19: 2700 | E19: 75600000
A20: 20K-50K | B20: 3 | C20: 31000 | D20: 2900 | E20: 269700000
A21: 50K-100K | B21: 2 | C21: 70000 | D21: 3200 | E21: 448000000
A22: GRAND TOTAL | B22: =B13+B23+B33+B37 | C22: 220000 | D22: 3500 | E22: =E13+E23+E33+E37
A23: Counties / Parishes subtotal | B23: =SUM(B16:B22) | E23: =SUM(E16:E22)
A25: Townships
A26: <1K | B26: 116 | C26: 450 | D26: 600 | E26: 31320000
A27: 1K-5K | B27: 71 | C27: 2700 | D27: 800 | E27: 153360000
A28: 5K-10K | B28: 18 | C28: 7100 | D28: 1100 | E28: 140580000
A29: 10K-20K | B29: 9 | C29: 14000 | D29: 1400 | E29: 176400000
A30: 20K-50K | B30: 5 | C30: 31000 | D30: 1600 | E30: 248000000
A31: 50K-100K | B31: 2 | C31: 70000 | D31: 1700 | E31: 238000000
A32: 100K+ | B32: 0 | C32: 220000 | D32: 1800 | E32: 0
A33: Townships subtotal | B33: 221 | E33: 987660000
A35: Special Districts
A36: (all sizes) | B36: 142 | D36: 7600000 | E36: 1079200000
A37: Special Districts subtotal | B37: 142 | E37: 1079200000

Sheet NJ
A1: NJ — New Jersey
A2: Counts and estimated annual operating spend by entity type and bucket.
A4: Entity / Bucket | B4: Count | C4: Avg Pop | D4: $/capita | E4: Spend ($)
A5: Municipalities
A6: <1K | B6: 130 | C6: 450 | D6: 2000 | E6: 117000000
A7: 1K-5K | B7: 142 | C7: 2700 | D7: 2500 | E7: 958500000
A8: 5K-10K | B8: 73 | C8: 7100 | D8: 3000 | E8: 1554900000
A9: 10K-20K | B9: 74 | C9: 14000 | D9: 3500 | E9: 3626000000
A10: 20K-50K | B10: 79 | C10: 31000 | D10: 4200 | E10: 10285800000
A11: 50K-100K | B11: 37 | C11: 70000 | D11: 4800 | E11: 12432000000
A12: 100K+ | B12: 30 | C12: 220000 | D12: 7000 | E12: 46200000000
A13: Municipalities subtotal | B13: 565 | E13: 75174200000
A15: Counties / Parishes
A16: <1K | B16: 0 | C16: 450 | D16: 3500 | E16: 0
A17: 1K-5K | B17: 1 | C17: 2700 | D17: 3300 | E17: 8910000
A18: 5K-10K | B18: 2 | C18: 7100 | D18: 2900 | E18: 41180000
A19: 10K-20K | B19: 3 | C19: 14000 | D19: 2700 | E19: 113400000
A20: 20K-50K | B20: 5 | C20: 31000 | D20: 2900 | E20: 449500000
A21: 50K-100K | B21: 4 | C21: 70000 | D21: 3200 | E21: 896000000
A22: GRAND TOTAL | B22: =B13+B23+B27 | C22: 220000 | D22: 3500 | E22: =E13+E23+E27
A23: Counties / Parishes subtotal | B23: =SUM(B16:B22) | E23: =SUM(E16:E22)
A25: Special Districts
A26: (all sizes) | B26: 281 | D26: 7600000 | E26: 2135600000
A27: Special Districts subtotal | B27: 281 | E27: 2135600000

Sheet NM
A1: NM — New Mexico
A2: Counts and estimated annual operating spend by entity type and bucket.
A4: Entity / Bucket | B4: Count | C4: Avg Pop | D4: $/capita | E4: Spend ($)
A5: Municipalities
A6: <1K | B6: 41 | C6: 450 | D6: 2000 | E6: 36900000
A7: 1K-5K | B7: 33 | C7: 2700 | D7: 2500 | E7: 222750000
A8: 5K-10K | B8: 12 | C8: 7100 | D8: 3000 | E8: 255600000
A9: 10K-20K | B9: 9 | C9: 14000 | D9: 3500 | E9: 441000000
A10: 20K-50K | B10: 7 | C10: 31000 | D10: 4200 | E10: 911400000
A11: 50K-100K | B11: 2 | C11: 70000 | D11: 4800 | E11: 672000000
A12: 100K+ | B12: 1 | C12: 220000 | D12: 7000 | E12: 1540000000
A13: Municipalities subtotal | B13: 105 | E13: 4079650000
A15: Counties / Parishes
A16: <1K | B16: 0 | C16: 450 | D16: 3500 | E16: 0
A17: 1K-5K | B17: 4 | C17: 2700 | D17: 3300 | E17: 35640000
A18: 5K-10K | B18: 4 | C18: 7100 | D18: 2900 | E18: 82360000
A19: 10K-20K | B19: 6 | C19: 14000 | D19: 2700 | E19: 226800000
A20: 20K-50K | B20: 9 | C20: 31000 | D20: 2900 | E20: 809100000
A21: 50K-100K | B21: 5 | C21: 70000 | D21: 3200 | E21: 1120000000
A22: GRAND TOTAL | B22: =B13+B23+B27 | C22: 220000 | D22: 3500 | E22: =E13+E23+E27
A23: Counties / Parishes subtotal | B23: =SUM(B16:B22) | E23: =SUM(E16:E22)
A25: Special Districts
A26: (all sizes) | B26: 685 | D26: 7600000 | E26: 5206000000
A27: Special Districts subtotal | B27: 685 | E27: 5206000000

Sheet NY
A1: NY — New York
A2: Counts and estimated annual operating spend by entity type and bucket.
A4: Entity / Bucket | B4: Count | C4: Avg Pop | D4: $/capita | E4: Spend ($)
A5: Municipalities
A6: <1K | B6: 142 | C6: 450 | D6: 2000 | E6: 127800000
A7: 1K-5K | B7: 155 | C7: 2700 | D7: 2500 | E7: 1046250000
A8: 5K-10K | B8: 79 | C8: 7100 | D8: 3000 | E8: 1682700000
A9: 10K-20K | B9: 81 | C9: 14000 | D9: 3500 | E9: 3969000000
A10: 20K-50K | B10: 85 | C10: 31000 | D10: 4200 | E10: 11067000000
A11: 50K-100K | B11: 40 | C11: 70000 | D11: 4800 | E11: 13440000000
A12: 100K+ | B12: 32 | C12: 220000 | D12: 7000 | E12: 49280000000
A13: Municipalities subtotal | B13: 614 | E13: 80612750000
A15: Counties / Parishes
A16: <1K | B16: 0 | C16: 450 | D16: 3500 | E16: 0
A17: 1K-5K | B17: 2 | C17: 2700 | D17: 3300 | E17: 17820000
A18: 5K-10K | B18: 4 | C18: 7100 | D18: 2900 | E18: 82360000
A19: 10K-20K | B19: 7 | C19: 14000 | D19: 2700 | E19: 264600000
A20: 20K-50K | B20: 15 | C20: 31000 | D20: 2900 | E20: 1348500000
A21: 50K-100K | B21: 12 | C21: 70000 | D21: 3200 | E21: 2688000000
A22: GRAND TOTAL | B22: =B13+B23+B33+B37 | C22: 220000 | D22: 3500 | E22: =E13+E23+E33+E37
A23: Counties / Parishes subtotal | B23: =SUM(B16:B22) | E23: =SUM(E16:E22)
A25: Townships
A26: <1K | B26: 368 | C26: 450 | D26: 600 | E26: 99360000
A27: 1K-5K | B27: 300 | C27: 2700 | D27: 800 | E27: 648000000
A28: 5K-10K | B28: 109 | C28: 7100 | D28: 1100 | E28: 851290000
A29: 10K-20K | B29: 74 | C29: 14000 | D29: 1400 | E29: 1450400000
A30: 20K-50K | B30: 58 | C30: 31000 | D30: 1600 | E30: 2876800000
A31: 50K-100K | B31: 24 | C31: 70000 | D31: 1700 | E31: 2856000000
A32: 100K+ | B32: 0 | C32: 220000 | D32: 1800 | E32: 0
A33: Townships subtotal | B33: 933 | E33: 8781850000
A35: Special Districts
A36: (all sizes) | B36: 1183 | D36: 7600000 | E36: 8990800000
A37: Special Districts subtotal | B37: 1183 | E37: 8990800000

Sheet NC
A1: NC — North Carolina
A2: Counts and estimated annual operating spend by entity type and bucket.
A4: Entity / Bucket | B4: Count | C4: Avg Pop | D4: $/capita | E4: Spend ($)
A5: Municipalities
A6: <1K | B6: 193 | C6: 450 | D6: 2000 | E6: 173700000
A7: 1K-5K | B7: 166 | C7: 2700 | D7: 2500 | E7: 1120500000
A8: 5K-10K | B8: 66 | C8: 7100 | D8: 3000 | E8: 1405800000
A9: 10K-20K | B9: 55 | C9: 14000 | D9: 3500 | E9: 2695000000
A10: 20K-50K | B10: 44 | C10: 31000 | D10: 4200 | E10: 5728800000
A11: 50K-100K | B11: 17 | C11: 70000 | D11: 4800 | E11: 5712000000
A12: 100K+ | B12: 11 | C12: 220000 | D12: 7000 | E12: 16940000000
A13: Municipalities subtotal | B13: 552 | E13: 33775800000
A15: Counties / Parishes
A16: <1K | B16: 1 | C16: 450 | D16: 3500 | E16: 1575000
A17: 1K-5K | B17: 8 | C17: 2700 | D17: 3300 | E17: 71280000
A18: 5K-10K | B18: 11 | C18: 7100 | D18: 2900 | E18: 226490000
A19: 10K-20K | B19: 17 | C19: 14000 | D19: 2700 | E19: 642600000
A20: 20K-50K | B20: 26 | C20: 31000 | D20: 2900 | E20: 2337400000
A21: 50K-100K | B21: 17 | C21: 70000 | D21: 3200 | E21: 3808000000
A22: GRAND TOTAL | B22: =B13+B23+B27 | C22: 220000 | D22: 3500 | E22: =E13+E23+E27
A23: Counties / Parishes subtotal | B23: =SUM(B16:B22) | E23: =SUM(E16:E22)
A25: Special Districts
A26: (all sizes) | B26: 311 | D26: 7600000 | E26: 2363600000
A27: Special Districts subtotal | B27: 311 | E27: 2363600000

Sheet ND
A1: ND — North Dakota
A2: Counts and estimated annual operating spend by entity type and bucket.
A4: Entity / Bucket | B4: Count | C4: Avg Pop | D4: $/capita | E4: Spend ($)
A5: Municipalities
A6: <1K | B6: 159 | C6: 450 | D6: 2000 | E6: 143100000
A7: 1K-5K | B7: 115 | C7: 2700 | D7: 2500 | E7: 776250000
A8: 5K-10K | B8: 37 | C8: 7100 | D8: 3000 | E8: 788100000
A9: 10K-20K | B9: 25 | C9: 14000 | D9: 3500 | E9: 1225000000
A10: 20K-50K | B10: 15 | C10: 31000 | D10: 4200 | E10: 1953000000
A11: 50K-100K | B11: 4 | C11: 70000 | D11: 4800 | E11: 1344000000
A12: 100K+ | B12: 2 | C12: 220000 | D12: 7000 | E12: 3080000000
A13: Municipalities subtotal | B13: 357 | E13: 9309450000
A15: Counties / Parishes
A16: <1K | B16: 1 | C16: 450 | D16: 3500 | E16: 1575000
A17: 1K-5K | B17: 8 | C17: 2700 | D17: 3300 | E17: 71280000
A18: 5K-10K | B18: 9 | C18: 7100 | D18: 2900 | E18: 185310000
A19: 10K-20K | B19: 11 | C19: 14000 | D19: 2700 | E19: 415800000
A20: 20K-50K | B20: 13 | C20: 31000 | D20: 2900 | E20: 1168700000
A21: 50K-100K | B21: 6 | C21: 70000 | D21: 3200 | E21: 1344000000
A22: GRAND TOTAL | B22: =B13+B23+B33+B37 | C22: 220000 | D22: 3500 | E22: =E13+E23+E33+E37
A23: Counties / Parishes subtotal | B23: =SUM(B16:B22) | E23: =SUM(E16:E22)
A25: Townships
A26: <1K | B26: 752 | C26: 450 | D26: 600 | E26: 203040000
A27: 1K-5K | B27: 403 | C27: 2700 | D27: 800 | E27: 870480000
A28: 5K-10K | B28: 92 | C28: 7100 | D28: 1100 | E28: 718520000
A29: 10K-20K | B29: 41 | C29: 14000 | D29: 1400 | E29: 803600000
A30: 20K-50K | B30: 19 | C30: 31000 | D30: 1600 | E30: 942400000
A31: 50K-100K | B31: 4 | C31: 70000 | D31: 1700 | E31: 476000000
A32: 100K+ | B32: 0 | C32: 220000 | D32: 1800 | E32: 0
A33: Townships subtotal | B33: 1311 | E33: 4014040000
A35: Special Districts
A36: (all sizes) | B36: 763 | D36: 7600000 | E36: 5798800000
A37: Special Districts subtotal | B37: 763 | E37: 5798800000

Sheet OH
A1: OH — Ohio
A2: Counts and estimated annual operating spend by entity type and bucket.
A4: Entity / Bucket | B4: Count | C4: Avg Pop | D4: $/capita | E4: Spend ($)
A5: Municipalities
A6: <1K | B6: 328 | C6: 450 | D6: 2000 | E6: 295200000
A7: 1K-5K | B7: 281 | C7: 2700 | D7: 2500 | E7: 1896750000
A8: 5K-10K | B8: 112 | C8: 7100 | D8: 3000 | E8: 2385600000
A9: 10K-20K | B9: 94 | C9: 14000 | D9: 3500 | E9: 4606000000
A10: 20K-50K | B10: 75 | C10: 31000 | D10: 4200 | E10: 9765000000
A11: 50K-100K | B11: 28 | C11: 70000 | D11: 4800 | E11: 9408000000
A12: 100K+ | B12: 19 | C12: 220000 | D12: 7000 | E12: 29260000000
A13: Municipalities subtotal | B13: 937 | E13: 57616550000
A15: Counties / Parishes
A16: <1K | B16: 1 | C16: 450 | D16: 3500 | E16: 1575000
A17: 1K-5K | B17: 7 | C17: 2700 | D17: 3300 | E17: 62370000
A18: 5K-10K | B18: 10 | C18: 7100 | D18: 2900 | E18: 205900000
A19: 10K-20K | B19: 15 | C19: 14000 | D19: 2700 | E19: 567000000
A20: 20K-50K | B20: 23 | C20: 31000 | D20: 2900 | E20: 2067700000
A21: 50K-100K | B21: 15 | C21: 70000 | D21: 3200 | E21: 3360000000
A22: GRAND TOTAL | B22: =B13+B23+B33+B37 | C22: 220000 | D22: 3500 | E22: =E13+E23+E33+E37
A23: Counties / Parishes subtotal | B23: =SUM(B16:B22) | E23: =SUM(E16:E22)
A25: Townships
A26: <1K | B26: 654 | C26: 450 | D26: 600 | E26: 176580000
A27: 1K-5K | B27: 419 | C27: 2700 | D27: 800 | E27: 905040000
A28: 5K-10K | B28: 118 | C28: 7100 | D28: 1100 | E28: 921580000
A29: 10K-20K | B29: 65 | C29: 14000 | D29: 1400 | E29: 1274000000
A30: 20K-50K | B30: 39 | C30: 31000 | D30: 1600 | E30: 1934400000
A31: 50K-100K | B31: 13 | C31: 70000 | D31: 1700 | E31: 1547000000
A32: 100K+ | B32: 0 | C32: 220000 | D32: 1800 | E32: 0
A33: Townships subtotal | B33: 1308 | E33: 6758600000
A35: Special Districts
A36: (all sizes) | B36: 776 | D36: 7600000 | E36: 5897600000
A37: Special Districts subtotal | B37: 776 | E37: 5897600000

Sheet OK
A1: OK — Oklahoma
A2: Counts and estimated annual operating spend by entity type and bucket.
A4: Entity / Bucket | B4: Count | C4: Avg Pop | D4: $/capita | E4: Spend ($)
A5: Municipalities
A6: <1K | B6: 231 | C6: 450 | D6: 2000 | E6: 207900000
A7: 1K-5K | B7: 190 | C7: 2700 | D7: 2500 | E7: 1282500000
A8: 5K-10K | B8: 69 | C8: 7100 | D8: 3000 | E8: 1469700000
A9: 10K-20K | B9: 52 | C9: 14000 | D9: 3500 | E9: 2548000000
A10: 20K-50K | B10: 38 | C10: 31000 | D10: 4200 | E10: 4947600000
A11: 50K-100K | B11: 12 | C11: 70000 | D11: 4800 | E11: 4032000000
A12: 100K+ | B12: 7 | C12: 220000 | D12: 7000 | E12: 10780000000
A13: Municipalities subtotal | B13: 599 | E13: 25267700000
A15: Counties / Parishes
A16: <1K | B16: 1 | C16: 450 | D16: 3500 | E16: 1575000
A17: 1K-5K | B17: 8 | C17: 2700 | D17: 3300 | E17: 71280000
A18: 5K-10K | B18: 10 | C18: 7100 | D18: 2900 | E18: 205900000
A19: 10K-20K | B19: 15 | C19: 14000 | D19: 2700 | E19: 567000000
A20: 20K-50K | B20: 20 | C20: 31000 | D20: 2900 | E20: 1798000000
A21: 50K-100K | B21: 12 | C21: 70000 | D21: 3200 | E21: 2688000000
A22: GRAND TOTAL | B22: =B13+B23+B27 | C22: 220000 | D22: 3500 | E22: =E13+E23+E27
A23: Counties / Parishes subtotal | B23: =SUM(B16:B22) | E23: =SUM(E16:E22)
A25: Special Districts
A26: (all sizes) | B26: 560 | D26: 7600000 | E26: 4256000000
A27: Special Districts subtotal | B27: 560 | E27: 4256000000

Sheet OR
A1: OR — Oregon
A2: Counts and estimated annual operating spend by entity type and bucket.
A4: Entity / Bucket | B4: Count | C4: Avg Pop | D4: $/capita | E4: Spend ($)
A5: Municipalities
A6: <1K | B6: 85 | C6: 450 | D6: 2000 | E6: 76500000
A7: 1K-5K | B7: 72 | C7: 2700 | D7: 2500 | E7: 486000000
A8: 5K-10K | B8: 29 | C8: 7100 | D8: 3000 | E8: 617700000
A9: 10K-20K | B9: 24 | C9: 14000 | D9: 3500 | E9: 1176000000
A10: 20K-50K | B10: 19 | C10: 31000 | D10: 4200 | E10: 2473800000
A11: 50K-100K | B11: 7 | C11: 70000 | D11: 4800 | E11: 2352000000
A12: 100K+ | B12: 5 | C12: 220000 | D12: 7000 | E12: 7700000000
A13: Municipalities subtotal | B13: 241 | E13: 14882000000
A15: Counties / Parishes
A16: <1K | B16: 1 | C16: 450 | D16: 3500 | E16: 1575000
A17: 1K-5K | B17: 3 | C17: 2700 | D17: 3300 | E17: 26730000
A18: 5K-10K | B18: 4 | C18: 7100 | D18: 2900 | E18: 82360000
A19: 10K-20K | B19: 6 | C19: 14000 | D19: 2700 | E19: 226800000
A20: 20K-50K | B20: 9 | C20: 31000 | D20: 2900 | E20: 809100000
A21: 50K-100K | B21: 6 | C21: 70000 | D21: 3200 | E21: 1344000000
A22: GRAND TOTAL | B22: =B13+B23+B27 | C22: 220000 | D22: 3500 | E22: =E13+E23+E27
A23: Counties / Parishes subtotal | B23: =SUM(B16:B22) | E23: =SUM(E16:E22)
A25: Special Districts
A26: (all sizes) | B26: 1057 | D26: 7600000 | E26: 8033200000
A27: Special Districts subtotal | B27: 1057 | E27: 8033200000

Sheet PA
A1: PA — Pennsylvania
A2: Counts and estimated annual operating spend by entity type and bucket.
A4: Entity / Bucket | B4: Count | C4: Avg Pop | D4: $/capita | E4: Spend ($)
A5: Municipalities
A6: <1K | B6: 355 | C6: 450 | D6: 2000 | E6: 319500000
A7: 1K-5K | B7: 305 | C7: 2700 | D7: 2500 | E7: 2058750000
A8: 5K-10K | B8: 122 | C8: 7100 | D8: 3000 | E8: 2598600000
A9: 10K-20K | B9: 102 | C9: 14000 | D9: 3500 | E9: 4998000000
A10: 20K-50K | B10: 81 | C10: 31000 | D10: 4200 | E10: 10546200000
A11: 50K-100K | B11: 30 | C11: 70000 | D11: 4800 | E11: 10080000000
A12: 100K+ | B12: 20 | C12: 220000 | D12: 7000 | E12: 30800000000
A13: Municipalities subtotal | B13: 1015 | E13: 61401050000
A15: Counties / Parishes
A16: <1K | B16: 1 | C16: 450 | D16: 3500 | E16: 1575000
A17: 1K-5K | B17: 5 | C17: 2700 | D17: 3300 | E17: 44550000
A18: 5K-10K | B18: 7 | C18: 7100 | D18: 2900 | E18: 144130000
A19: 10K-20K | B19: 11 | C19: 14000 | D19: 2700 | E19: 415800000
A20: 20K-50K | B20: 18 | C20: 31000 | D20: 2900 | E20: 1618200000
A21: 50K-100K | B21: 11 | C21: 70000 | D21: 3200 | E21: 2464000000
A22: GRAND TOTAL | B22: =B13+B23+B33+B37 | C22: 220000 | D22: 3500 | E22: =E13+E23+E33+E37
A23: Counties / Parishes subtotal | B23: =SUM(B16:B22) | E23: =SUM(E16:E22)
A25: Townships
A26: <1K | B26: 773 | C26: 450 | D26: 600 | E26: 208710000
A27: 1K-5K | B27: 495 | C27: 2700 | D27: 800 | E27: 1069200000
A28: 5K-10K | B28: 139 | C28: 7100 | D28: 1100 | E28: 1085590000
A29: 10K-20K | B29: 77 | C29: 14000 | D29: 1400 | E29: 1509200000
A30: 20K-50K | B30: 46 | C30: 31000 | D30: 1600 | E30: 2281600000
A31: 50K-100K | B31: 16 | C31: 70000 | D31: 1700 | E31: 1904000000
A32: 100K+ | B32: 0 | C32: 220000 | D32: 1800 | E32: 0
A33: Townships subtotal | B33: 1546 | E33: 8058300000
A35: Special Districts
A36: (all sizes) | B36: 1620 | D36: 7600000 | E36: 12312000000
A37: Special Districts subtotal | B37: 1620 | E37: 12312000000

Sheet RI
A1: RI — Rhode Island
A2: Counts and estimated annual operating spend by entity type and bucket.
A4: Entity / Bucket | B4: Count | C4: Avg Pop | D4: $/capita | E4: Spend ($)
A5: Municipalities
A6: <1K | B6: 3 | C6: 450 | D6: 2000 | E6: 2700000
A7: 1K-5K | B7: 2 | C7: 2700 | D7: 2500 | E7: 13500000
A8: 5K-10K | B8: 1 | C8: 7100 | D8: 3000 | E8: 21300000
A9: 10K-20K | B9: 1 | C9: 14000 | D9: 3500 | E9: 49000000
A10: 20K-50K | B10: 1 | C10: 31000 | D10: 4200 | E10: 130200000
A11: 50K-100K | B11: 0 | C11: 70000 | D11: 4800 | E11: 0
A12: 100K+ | B12: 0 | C12: 220000 | D12: 7000 | E12: 0
A13: Municipalities subtotal | B13: 8 | E13: 216700000
A15: Counties / Parishes
A16: <1K | B16: 0 | C16: 450 | D16: 3500 | E16: 0
A17: 1K-5K | B17: 0 | C17: 2700 | D17: 3300 | E17: 0
A18: 5K-10K | B18: 0 | C18: 7100 | D18: 2900 | E18: 0
A19: 10K-20K | B19: 0 | C19: 14000 | D19: 2700 | E19: 0
A20: 20K-50K | B20: 0 | C20: 31000 | D20: 2900 | E20: 0
A21: 50K-100K | B21: 0 | C21: 70000 | D21: 3200 | E21: 0
A22: GRAND TOTAL | B22: =B13+B23+B33+B37 | C22: 220000 | D22: 3500 | E22: =E13+E23+E33+E37
A23: Counties / Parishes subtotal | B23: =SUM(B16:B22) | E23: =SUM(E16:E22)
A25: Townships
A26: <1K | B26: 14 | C26: 450 | D26: 600 | E26: 3780000
A27: 1K-5K | B27: 10 | C27: 2700 | D27: 800 | E27: 21600000
A28: 5K-10K | B28: 3 | C28: 7100 | D28: 1100 | E28: 23430000
A29: 10K-20K | B29: 2 | C29: 14000 | D29: 1400 | E29: 39200000
A30: 20K-50K | B30: 1 | C30: 31000 | D30: 1600 | E30: 49600000
A31: 50K-100K | B31: 1 | C31: 70000 | D31: 1700 | E31: 119000000
A32: 100K+ | B32: 0 | C32: 220000 | D32: 1800 | E32: 0
A33: Townships subtotal | B33: 31 | E33: 256610000
A35: Special Districts
A36: (all sizes) | B36: 84 | D36: 7600000 | E36: 638400000
A37: Special Districts subtotal | B37: 84 | E37: 638400000

Sheet SC
A1: SC — South Carolina
A2: Counts and estimated annual operating spend by entity type and bucket.
A4: Entity / Bucket | B4: Count | C4: Avg Pop | D4: $/capita | E4: Spend ($)
A5: Municipalities
A6: <1K | B6: 95 | C6: 450 | D6: 2000 | E6: 85500000
A7: 1K-5K | B7: 81 | C7: 2700 | D7: 2500 | E7: 546750000
A8: 5K-10K | B8: 33 | C8: 7100 | D8: 3000 | E8: 702900000
A9: 10K-20K | B9: 27 | C9: 14000 | D9: 3500 | E9: 1323000000
A10: 20K-50K | B10: 22 | C10: 31000 | D10: 4200 | E10: 2864400000
A11: 50K-100K | B11: 8 | C11: 70000 | D11: 4800 | E11: 2688000000
A12: 100K+ | B12: 5 | C12: 220000 | D12: 7000 | E12: 7700000000
A13: Municipalities subtotal | B13: 271 | E13: 15910550000
A15: Counties / Parishes
A16: <1K | B16: 0 | C16: 450 | D16: 3500 | E16: 0
A17: 1K-5K | B17: 4 | C17: 2700 | D17: 3300 | E17: 35640000
A18: 5K-10K | B18: 5 | C18: 7100 | D18: 2900 | E18: 102950000
A19: 10K-20K | B19: 8 | C19: 14000 | D19: 2700 | E19: 302400000
A20: 20K-50K | B20: 12 | C20: 31000 | D20: 2900 | E20: 1078800000
A21: 50K-100K | B21: 8 | C21: 70000 | D21: 3200 | E21: 1792000000
A22: GRAND TOTAL | B22: =B13+B23+B27 | C22: 220000 | D22: 3500 | E22: =E13+E23+E27
A23: Counties / Parishes subtotal | B23: =SUM(B16:B22) | E23: =SUM(E16:E22)
A25: Special Districts
A26: (all sizes) | B26: 297 | D26: 7600000 | E26: 2257200000
A27: Special Districts subtotal | B27: 297 | E27: 2257200000

Sheet SD
A1: SD — South Dakota
A2: Counts and estimated annual operating spend by entity type and bucket.
A4: Entity / Bucket | B4: Count | C4: Avg Pop | D4: $/capita | E4: Spend ($)
A5: Municipalities
A6: <1K | B6: 139 | C6: 450 | D6: 2000 | E6: 125100000
A7: 1K-5K | B7: 100 | C7: 2700 | D7: 2500 | E7: 675000000
A8: 5K-10K | B8: 32 | C8: 7100 | D8: 3000 | E8: 681600000
A9: 10K-20K | B9: 22 | C9: 14000 | D9: 3500 | E9: 1078000000
A10: 20K-50K | B10: 13 | C10: 31000 | D10: 4200 | E10: 1692600000
A11: 50K-100K | B11: 3 | C11: 70000 | D11: 4800 | E11: 1008000000
A12: 100K+ | B12: 2 | C12: 220000 | D12: 7000 | E12: 3080000000
A13: Municipalities subtotal | B13: 311 | E13: 8340300000
A15: Counties / Parishes
A16: <1K | B16: 2 | C16: 450 | D16: 3500 | E16: 3150000
A17: 1K-5K | B17: 10 | C17: 2700 | D17: 3300 | E17: 89100000
A18: 5K-10K | B18: 11 | C18: 7100 | D18: 2900 | E18: 226490000
A19: 10K-20K | B19: 14 | C19: 14000 | D19: 2700 | E19: 529200000
A20: 20K-50K | B20: 16 | C20: 31000 | D20: 2900 | E20: 1438400000
A21: 50K-100K | B21: 7 | C21: 70000 | D21: 3200 | E21: 1568000000
A22: GRAND TOTAL | B22: =B13+B23+B33+B37 | C22: 220000 | D22: 3500 | E22: =E13+E23+E33+E37
A23: Counties / Parishes subtotal | B23: =SUM(B16:B22) | E23: =SUM(E16:E22)
A25: Townships
A26: <1K | B26: 528 | C26: 450 | D26: 600 | E26: 142560000
A27: 1K-5K | B27: 284 | C27: 2700 | D27: 800 | E27: 613440000
A28: 5K-10K | B28: 64 | C28: 7100 | D28: 1100 | E28: 499840000
A29: 10K-20K | B29: 29 | C29: 14000 | D29: 1400 | E29: 568400000
A30: 20K-50K | B30: 13 | C30: 31000 | D30: 1600 | E30: 644800000
A31: 50K-100K | B31: 3 | C31: 70000 | D31: 1700 | E31: 357000000
A32: 100K+ | B32: 0 | C32: 220000 | D32: 1800 | E32: 0
A33: Townships subtotal | B33: 921 | E33: 2826040000
A35: Special Districts
A36: (all sizes) | B36: 350 | D36: 7600000 | E36: 2660000000
A37: Special Districts subtotal | B37: 350 | E37: 2660000000

Sheet TN
A1: TN — Tennessee
A2: Counts and estimated annual operating spend by entity type and bucket.
A4: Entity / Bucket | B4: Count | C4: Avg Pop | D4: $/capita | E4: Spend ($)
A5: Municipalities
A6: <1K | B6: 121 | C6: 450 | D6: 2000 | E6: 108900000
A7: 1K-5K | B7: 103 | C7: 2700 | D7: 2500 | E7: 695250000
A8: 5K-10K | B8: 41 | C8: 7100 | D8: 3000 | E8: 873300000
A9: 10K-20K | B9: 35 | C9: 14000 | D9: 3500 | E9: 1715000000
A10: 20K-50K | B10: 28 | C10: 31000 | D10: 4200 | E10: 3645600000
A11: 50K-100K | B11: 10 | C11: 70000 | D11: 4800 | E11: 3360000000
A12: 100K+ | B12: 7 | C12: 220000 | D12: 7000 | E12: 10780000000
A13: Municipalities subtotal | B13: 345 | E13: 21178050000
A15: Counties / Parishes
A16: <1K | B16: 1 | C16: 450 | D16: 3500 | E16: 1575000
A17: 1K-5K | B17: 7 | C17: 2700 | D17: 3300 | E17: 62370000
A18: 5K-10K | B18: 10 | C18: 7100 | D18: 2900 | E18: 205900000
A19: 10K-20K | B19: 16 | C19: 14000 | D19: 2700 | E19: 604800000
A20: 20K-50K | B20: 24 | C20: 31000 | D20: 2900 | E20: 2157600000
A21: 50K-100K | B21: 16 | C21: 70000 | D21: 3200 | E21: 3584000000
A22: GRAND TOTAL | B22: =B13+B23+B27 | C22: 220000 | D22: 3500 | E22: =E13+E23+E27
A23: Counties / Parishes subtotal | B23: =SUM(B16:B22) | E23: =SUM(E16:E22)
A25: Special Districts
A26: (all sizes) | B26: 525 | D26: 7600000 | E26: 3990000000
A27: Special Districts subtotal | B27: 525 | E27: 3990000000

Sheet TX
A1: TX — Texas
A2: Counts and estimated annual operating spend by entity type and bucket.
A4: Entity / Bucket | B4: Count | C4: Avg Pop | D4: $/capita | E4: Spend ($)
A5: Municipalities
A6: <1K | B6: 364 | C6: 450 | D6: 2000 | E6: 327600000
A7: 1K-5K | B7: 351 | C7: 2700 | D7: 2500 | E7: 2369250000
A8: 5K-10K | B8: 156 | C8: 7100 | D8: 3000 | E8: 3322800000
A9: 10K-20K | B9: 136 | C9: 14000 | D9: 3500 | E9: 6664000000
A10: 20K-50K | B10: 125 | C10: 31000 | D10: 4200 | E10: 16275000000
A11: 50K-100K | B11: 51 | C11: 70000 | D11: 4800 | E11: 17136000000
A12: 100K+ | B12: 38 | C12: 220000 | D12: 7000 | E12: 58520000000
A13: Municipalities subtotal | B13: 1221 | E13: 104614650000
A15: Counties / Parishes
A16: <1K | B16: 2 | C16: 450 | D16: 3500 | E16: 3150000
A17: 1K-5K | B17: 15 | C17: 2700 | D17: 3300 | E17: 133650000
A18: 5K-10K | B18: 23 | C18: 7100 | D18: 2900 | E18: 473570000
A19: 10K-20K | B19: 38 | C19: 14000 | D19: 2700 | E19: 1436400000
A20: 20K-50K | B20: 67 | C20: 31000 | D20: 2900 | E20: 6023300000
A21: 50K-100K | B21: 47 | C21: 70000 | D21: 3200 | E21: 10528000000
A22: GRAND TOTAL | B22: =B13+B23+B27 | C22: 220000 | D22: 3500 | E22: =E13+E23+E27
A23: Counties / Parishes subtotal | B23: =SUM(B16:B22) | E23: =SUM(E16:E22)
A25: Special Districts
A26: (all sizes) | B26: 3100 | D26: 7600000 | E26: 23560000000
A27: Special Districts subtotal | B27: 3100 | E27: 23560000000

Sheet UT
A1: UT — Utah
A2: Counts and estimated annual operating spend by entity type and bucket.
A4: Entity / Bucket | B4: Count | C4: Avg Pop | D4: $/capita | E4: Spend ($)
A5: Municipalities
A6: <1K | B6: 74 | C6: 450 | D6: 2000 | E6: 66600000
A7: 1K-5K | B7: 71 | C7: 2700 | D7: 2500 | E7: 479250000
A8: 5K-10K | B8: 32 | C8: 7100 | D8: 3000 | E8: 681600000
A9: 10K-20K | B9: 28 | C9: 14000 | D9: 3500 | E9: 1372000000
A10: 20K-50K | B10: 25 | C10: 31000 | D10: 4200 | E10: 3255000000
A11: 50K-100K | B11: 10 | C11: 70000 | D11: 4800 | E11: 3360000000
A12: 100K+ | B12: 8 | C12: 220000 | D12: 7000 | E12: 12320000000
A13: Municipalities subtotal | B13: 248 | E13: 21534450000
A15: Counties / Parishes
A16: <1K | B16: 0 | C16: 450 | D16: 3500 | E16: 0
A17: 1K-5K | B17: 2 | C17: 2700 | D17: 3300 | E17: 17820000
A18: 5K-10K | B18: 3 | C18: 7100 | D18: 2900 | E18: 61770000
A19: 10K-20K | B19: 4 | C19: 14000 | D19: 2700 | E19: 151200000
A20: 20K-50K | B20: 8 | C20: 31000 | D20: 2900 | E20: 719200000
A21: 50K-100K | B21: 5 | C21: 70000 | D21: 3200 | E21: 1120000000
A22: GRAND TOTAL | B22: =B13+B23+B27 | C22: 220000 | D22: 3500 | E22: =E13+E23+E27
A23: Counties / Parishes subtotal | B23: =SUM(B16:B22) | E23: =SUM(E16:E22)
A25: Special Districts
A26: (all sizes) | B26: 1129 | D26: 7600000 | E26: 8580400000
A27: Special Districts subtotal | B27: 1129 | E27: 8580400000

Sheet VT
A1: VT — Vermont
A2: Counts and estimated annual operating spend by entity type and bucket.
A4: Entity / Bucket | B4: Count | C4: Avg Pop | D4: $/capita | E4: Spend ($)
A5: Municipalities
A6: <1K | B6: 21 | C6: 450 | D6: 2000 | E6: 18900000
A7: 1K-5K | B7: 15 | C7: 2700 | D7: 2500 | E7: 101250000
A8: 5K-10K | B8: 5 | C8: 7100 | D8: 3000 | E8: 106500000
A9: 10K-20K | B9: 3 | C9: 14000 | D9: 3500 | E9: 147000000
A10: 20K-50K | B10: 2 | C10: 31000 | D10: 4200 | E10: 260400000
A11: 50K-100K | B11: 1 | C11: 70000 | D11: 4800 | E11: 336000000
A12: 100K+ | B12: 0 | C12: 220000 | D12: 7000 | E12: 0
A13: Municipalities subtotal | B13: 47 | E13: 970050000
A15: Counties / Parishes
A16: <1K | B16: 0 | C16: 450 | D16: 3500 | E16: 0
A17: 1K-5K | B17: 2 | C17: 2700 | D17: 3300 | E17: 17820000
A18: 5K-10K | B18: 2 | C18: 7100 | D18: 2900 | E18: 41180000
A19: 10K-20K | B19: 3 | C19: 14000 | D19: 2700 | E19: 113400000
A20: 20K-50K | B20: 4 | C20: 31000 | D20: 2900 | E20: 359600000
A21: 50K-100K | B21: 2 | C21: 70000 | D21: 3200 | E21: 448000000
A22: GRAND TOTAL | B22: =B13+B23+B33+B37 | C22: 220000 | D22: 3500 | E22: =E13+E23+E33+E37
A23: Counties / Parishes subtotal | B23: =SUM(B16:B22) | E23: =SUM(E16:E22)
A25: Townships
A26: <1K | B26: 136 | C26: 450 | D26: 600 | E26: 36720000
A27: 1K-5K | B27: 73 | C27: 2700 | D27: 800 | E27: 157680000
A28: 5K-10K | B28: 17 | C28: 7100 | D28: 1100 | E28: 132770000
A29: 10K-20K | B29: 7 | C29: 14000 | D29: 1400 | E29: 137200000
A30: 20K-50K | B30: 3 | C30: 31000 | D30: 1600 | E30: 148800000
A31: 50K-100K | B31: 1 | C31: 70000 | D31: 1700 | E31: 119000000
A32: 100K+ | B32: 0 | C32: 220000 | D32: 1800 | E32: 0
A33: Townships subtotal | B33: 237 | E33: 732170000
A35: Special Districts
A36: (all sizes) | B36: 156 | D36: 7600000 | E36: 1185600000
A37: Special Districts subtotal | B37: 156 | E37: 1185600000

Sheet VA
A1: VA — Virginia
A2: Counts and estimated annual operating spend by entity type and bucket.
A4: Entity / Bucket | B4: Count | C4: Avg Pop | D4: $/capita | E4: Spend ($)
A5: Municipalities
A6: <1K | B6: 80 | C6: 450 | D6: 2000 | E6: 72000000
A7: 1K-5K | B7: 69 | C7: 2700 | D7: 2500 | E7: 465750000
A8: 5K-10K | B8: 27 | C8: 7100 | D8: 3000 | E8: 575100000
A9: 10K-20K | B9: 23 | C9: 14000 | D9: 3500 | E9: 1127000000
A10: 20K-50K | B10: 18 | C10: 31000 | D10: 4200 | E10: 2343600000
A11: 50K-100K | B11: 7 | C11: 70000 | D11: 4800 | E11: 2352000000
A12: 100K+ | B12: 5 | C12: 220000 | D12: 7000 | E12: 7700000000
A13: Municipalities subtotal | B13: 229 | E13: 14635450000
A15: Counties / Parishes
A16: <1K | B16: 1 | C16: 450 | D16: 3500 | E16: 1575000
A17: 1K-5K | B17: 8 | C17: 2700 | D17: 3300 | E17: 71280000
A18: 5K-10K | B18: 10 | C18: 7100 | D18: 2900 | E18: 205900000
A19: 10K-20K | B19: 16 | C19: 14000 | D19: 2700 | E19: 604800000
A20: 20K-50K | B20: 25 | C20: 31000 | D20: 2900 | E20: 2247500000
A21: 50K-100K | B21: 16 | C21: 70000 | D21: 3200 | E21: 3584000000
A22: GRAND TOTAL | B22: =B13+B23+B27 | C22: 220000 | D22: 3500 | E22: =E13+E23+E27
A23: Counties / Parishes subtotal | B23: =SUM(B16:B22) | E23: =SUM(E16:E22)
A25: Special Districts
A26: (all sizes) | B26: 195 | D26: 7600000 | E26: 1482000000
A27: Special Districts subtotal | B27: 195 | E27: 1482000000

Sheet WA
A1: WA — Washington
A2: Counts and estimated annual operating spend by entity type and bucket.
A4: Entity / Bucket | B4: Count | C4: Avg Pop | D4: $/capita | E4: Spend ($)
A5: Municipalities
A6: <1K | B6: 84 | C6: 450 | D6: 2000 | E6: 75600000
A7: 1K-5K | B7: 81 | C7: 2700 | D7: 2500 | E7: 546750000
A8: 5K-10K | B8: 36 | C8: 7100 | D8: 3000 | E8: 766800000
A9: 10K-20K | B9: 31 | C9: 14000 | D9: 3500 | E9: 1519000000
A10: 20K-50K | B10: 29 | C10: 31000 | D10: 4200 | E10: 3775800000
A11: 50K-100K | B11: 11 | C11: 70000 | D11: 4800 | E11: 3696000000
A12: 100K+ | B12: 9 | C12: 220000 | D12: 7000 | E12: 13860000000
A13: Municipalities subtotal | B13: 281 | E13: 24239950000
A15: Counties / Parishes
A16: <1K | B16: 0 | C16: 450 | D16: 3500 | E16: 0
A17: 1K-5K | B17: 2 | C17: 2700 | D17: 3300 | E17: 17820000
A18: 5K-10K | B18: 4 | C18: 7100 | D18: 2900 | E18: 82360000
A19: 10K-20K | B19: 6 | C19: 14000 | D19: 2700 | E19: 226800000
A20: 20K-50K | B20: 10 | C20: 31000 | D20: 2900 | E20: 899000000
A21: 50K-100K | B21: 7 | C21: 70000 | D21: 3200 | E21: 1568000000
A22: GRAND TOTAL | B22: =B13+B23+B27 | C22: 220000 | D22: 3500 | E22: =E13+E23+E27
A23: Counties / Parishes subtotal | B23: =SUM(B16:B22) | E23: =SUM(E16:E22)
A25: Special Districts
A26: (all sizes) | B26: 1336 | D26: 7600000 | E26: 10153600000
A27: Special Districts subtotal | B27: 1336 | E27: 10153600000

Sheet WV
A1: WV — West Virginia
A2: Counts and estimated annual operating spend by entity type and bucket.
A4: Entity / Bucket | B4: Count | C4: Avg Pop | D4: $/capita | E4: Spend ($)
A5: Municipalities
A6: <1K | B6: 89 | C6: 450 | D6: 2000 | E6: 80100000
A7: 1K-5K | B7: 74 | C7: 2700 | D7: 2500 | E7: 499500000
A8: 5K-10K | B8: 27 | C8: 7100 | D8: 3000 | E8: 575100000
A9: 10K-20K | B9: 20 | C9: 14000 | D9: 3500 | E9: 980000000
A10: 20K-50K | B10: 14 | C10: 31000 | D10: 4200 | E10: 1822800000
A11: 50K-100K | B11: 5 | C11: 70000 | D11: 4800 | E11: 1680000000
A12: 100K+ | B12: 3 | C12: 220000 | D12: 7000 | E12: 4620000000
A13: Municipalities subtotal | B13: 232 | E13: 10257500000
A15: Counties / Parishes
A16: <1K | B16: 1 | C16: 450 | D16: 3500 | E16: 1575000
A17: 1K-5K | B17: 6 | C17: 2700 | D17: 3300 | E17: 53460000
A18: 5K-10K | B18: 8 | C18: 7100 | D18: 2900 | E18: 164720000
A19: 10K-20K | B19: 10 | C19: 14000 | D19: 2700 | E19: 378000000
A20: 20K-50K | B20: 14 | C20: 31000 | D20: 2900 | E20: 1258600000
A21: 50K-100K | B21: 8 | C21: 70000 | D21: 3200 | E21: 1792000000
A22: GRAND TOTAL | B22: =B13+B23+B27 | C22: 220000 | D22: 3500 | E22: =E13+E23+E27
A23: Counties / Parishes subtotal | B23: =SUM(B16:B22) | E23: =SUM(E16:E22)
A25: Special Districts
A26: (all sizes) | B26: 358 | D26: 7600000 | E26: 2720800000
A27: Special Districts subtotal | B27: 358 | E27: 2720800000

Sheet WI
A1: WI — Wisconsin
A2: Counts and estimated annual operating spend by entity type and bucket.
A4: Entity / Bucket | B4: Count | C4: Avg Pop | D4: $/capita | E4: Spend ($)
A5: Municipalities
A6: <1K | B6: 208 | C6: 450 | D6: 2000 | E6: 187200000
A7: 1K-5K | B7: 179 | C7: 2700 | D7: 2500 | E7: 1208250000
A8: 5K-10K | B8: 71 | C8: 7100 | D8: 3000 | E8: 1512300000
A9: 10K-20K | B9: 60 | C9: 14000 | D9: 3500 | E9: 2940000000
A10: 20K-50K | B10: 48 | C10: 31000 | D10: 4200 | E10: 6249600000
A11: 50K-100K | B11: 18 | C11: 70000 | D11: 4800 | E11: 6048000000
A12: 100K+ | B12: 12 | C12: 220000 | D12: 7000 | E12: 18480000000
A13: Municipalities subtotal | B13: 596 | E13: 36625350000
A15: Counties / Parishes
A16: <1K | B16: 1 | C16: 450 | D16: 3500 | E16: 1575000
A17: 1K-5K | B17: 6 | C17: 2700 | D17: 3300 | E17: 53460000
A18: 5K-10K | B18: 8 | C18: 7100 | D18: 2900 | E18: 164720000
A19: 10K-20K | B19: 12 | C19: 14000 | D19: 2700 | E19: 453600000
A20: 20K-50K | B20: 19 | C20: 31000 | D20: 2900 | E20: 1708100000
A21: 50K-100K | B21: 12 | C21: 70000 | D21: 3200 | E21: 2688000000
A22: GRAND TOTAL | B22: =B13+B23+B33+B37 | C22: 220000 | D22: 3500 | E22: =E13+E23+E33+E37
A23: Counties / Parishes subtotal | B23: =SUM(B16:B22) | E23: =SUM(E16:E22)
A25: Townships
A26: <1K | B26: 627 | C26: 450 | D26: 600 | E26: 169290000
A27: 1K-5K | B27: 402 | C27: 2700 | D27: 800 | E27: 868320000
A28: 5K-10K | B28: 113 | C28: 7100 | D28: 1100 | E28: 882530000
A29: 10K-20K | B29: 63 | C29: 14000 | D29: 1400 | E29: 1234800000
A30: 20K-50K | B30: 38 | C30: 31000 | D30: 1600 | E30: 1884800000
A31: 50K-100K | B31: 12 | C31: 70000 | D31: 1700 | E31: 1428000000
A32: 100K+ | B32: 0 | C32: 220000 | D32: 1800 | E32: 0
A33: Townships subtotal | B33: 1255 | E33: 6467740000
A35: Special Districts
A36: (all sizes) | B36: 730 | D36: 7600000 | E36: 5548000000
A37: Special Districts subtotal | B37: 730 | E37: 5548000000

Sheet WY
A1: WY — Wyoming
A2: Counts and estimated annual operating spend by entity type and bucket.
A4: Entity / Bucket | B4: Count | C4: Avg Pop | D4: $/capita | E4: Spend ($)
A5: Municipalities
A6: <1K | B6: 44 | C6: 450 | D6: 2000 | E6: 39600000
A7: 1K-5K | B7: 32 | C7: 2700 | D7: 2500 | E7: 216000000
A8: 5K-10K | B8: 10 | C8: 7100 | D8: 3000 | E8: 213000000
A9: 10K-20K | B9: 7 | C9: 14000 | D9: 3500 | E9: 343000000
A10: 20K-50K | B10: 4 | C10: 31000 | D10: 4200 | E10: 520800000
A11: 50K-100K | B11: 1 | C11: 70000 | D11: 4800 | E11: 336000000
A12: 100K+ | B12: 1 | C12: 220000 | D12: 7000 | E12: 1540000000
A13: Municipalities subtotal | B13: 99 | E13: 3208400000
A15: Counties / Parishes
A16: <1K | B16: 0 | C16: 450 | D16: 3500 | E16: 0
A17: 1K-5K | B17: 3 | C17: 2700 | D17: 3300 | E17: 26730000
A18: 5K-10K | B18: 4 | C18: 7100 | D18: 2900 | E18: 82360000
A19: 10K-20K | B19: 5 | C19: 14000 | D19: 2700 | E19: 189000000
A20: 20K-50K | B20: 6 | C20: 31000 | D20: 2900 | E20: 539400000
A21: 50K-100K | B21: 3 | C21: 70000 | D21: 3200 | E21: 672000000
A22: GRAND TOTAL | B22: =B13+B23+B27 | C22: 220000 | D22: 3500 | E22: =E13+E23+E27
A23: Counties / Parishes subtotal | B23: =SUM(B16:B22) | E23: =SUM(E16:E22)
A25: Special Districts
A26: (all sizes) | B26: 683 | D26: 7600000 | E26: 5190800000
A27: Special Districts subtotal | B27: 683 | E27: 5190800000

Sheet DC
A1: DC — District of Columbia
A2: Counts and estimated annual operating spend by entity type and bucket.
A4: Entity / Bucket | B4: Count | C4: Avg Pop | D4: $/capita | E4: Spend ($)
A5: Municipalities
A6: <1K | B6: 0 | C6: 450 | D6: 2000 | E6: 0
A7: 1K-5K | B7: 1 | C7: 2700 | D7: 2500 | E7: 6750000
A8: 5K-10K | B8: 0 | C8: 7100 | D8: 3000 | E8: 0
A9: 10K-20K | B9: 0 | C9: 14000 | D9: 3500 | E9: 0
A10: 20K-50K | B10: 0 | C10: 31000 | D10: 4200 | E10: 0
A11: 50K-100K | B11: 0 | C11: 70000 | D11: 4800 | E11: 0
A12: 100K+ | B12: 0 | C12: 220000 | D12: 7000 | E12: 0
A13: Municipalities subtotal | B13: 1 | E13: 6750000
A15: Counties / Parishes
A16: <1K | B16: 0 | C16: 450 | D16: 3500 | E16: 0
A17: 1K-5K | B17: 0 | C17: 2700 | D17: 3300 | E17: 0
A18: 5K-10K | B18: 0 | C18: 7100 | D18: 2900 | E18: 0
A19: 10K-20K | B19: 0 | C19: 14000 | D19: 2700 | E19: 0
A20: 20K-50K | B20: 0 | C20: 31000 | D20: 2900 | E20: 0
A21: 50K-100K | B21: 0 | C21: 70000 | D21: 3200 | E21: 0
A22: GRAND TOTAL | B22: =B13+B23+B27 | C22: 220000 | D22: 3500 | E22: =E13+E23+E27
A23: Counties / Parishes subtotal | B23: =SUM(B16:B22) | E23: =SUM(E16:E22)
A25: Special Districts
A26: (all sizes) | B26: 1 | D26: 7600000 | E26: 7600000
A27: Special Districts subtotal | B27: 1 | E27: 7600000

Sheet Competitor Summary
A1: Competitor Summary
A2: Per-vendor profile across the U.S. local-government software market.
A4: Vendor | B4: HQ | C4: Customers (published) | D4: Customers (allocated) | E4: Calibration Δ | F4: Focus | G4: Size Target | H4: Top State | I4: #2 State | J4: Notes
A5: Tyler Technologies | B5: TX (Texas) | C5: 13000 | D5: 12490 | E5: -0.039230769 | F5: Enterprise ERP, courts, public safety, K-12, payments | G5: Mid-to-large (10K-100K+) | H5: TX (1100) | I5: CA (750) | J5: Largest pure-play public-sector software vendor. NIC acquisition (2021, $2.3B) added payments + 30 state portal contracts. Strong in county courts, ERP (Munis), CAD/RMS (New World).
A6: BS&A Software | B6: MI (Michigan) | C6: 2500 | D6: 2482 | E6: -0.0072 | F6: Financial mgmt, assessing, tax, building permits | G6: Small-to-mid (1K-50K) | H6: MI (1450) | I6: OH (220) | J6: Michigan dominant — estimated ~70-80% of MI municipalities run BS&A. Acquired by Harris Computer (Constellation Software) in 2021. Expanding into OH, IN, IL via Harris's distribution.
A7: Caselle | B7: UT (Utah) | C7: 1000 | D7: 1130 | E7: 0.13 | F7: Accounting, payroll, utility billing for small cities | G7: Small (<10K) | H7: UT (280) | I7: ID (110) | J7: Mountain-West small-town stronghold. Long-tenured installed base in UT/ID/WY/MT/NV. Slower modernization than some peers; core suite still stable cash cow.
A8: gWorks | B8: NE (Nebraska) | C8: 2500 | D8: 2635 | E8: 0.054 | F8: All-in-one ERP, GIS, websites for very small towns | G8: Very small (<5K) | H8: NE (480) | I8: IA (280) | J8: Roll-up of small public-sector vendors. Acquired Banyon Data Systems (MN), Pontem, and others. Plains-states stronghold; expanding eastward via channel.
A9: Muni-Link | B9: PA (Pennsylvania) | C9: 750 | D9: 840 | E9: 0.12 | F9: Cloud utility billing (water, sewer, stormwater) | G9: Small-to-mid utilities (1K-50K) | H9: PA (220) | I9: OH (100) | J9: Single-vertical SaaS focused on municipal utility billing. Concentrated in PA/OH/WV with growing presence in NY/MD/VA. Often layered alongside a separate ERP.
A10: TownCloud | B10: VA (Virginia) | C10: 200 | D10: 212 | E10: 0.06 | F10: Cloud-native ERP for small Southeast towns | G10: Small (<5K) | H10: VA (50) | I10: NC (30) | J10: Newer entrant. Cloud-native from day one. Concentrated in VA/NC/SC/TN. Smaller footprint but fastest growth rate among the tracked set.

Sheet Competitor Penetration
A1: Competitor Penetration — State × Vendor matrix
A2: Cells = customer count by state. Combined Penetration % = total tracked-vendor customers ÷ (counties + munis + townships) in that state.
A4: State | B4: Counties | C4: Munis | D4: Townships | E4: Addressable (C+M+T) | F4: Tyler Technologies | G4: BS&A Software | H4: Caselle | I4: gWorks | J4: Muni-Link | K4: TownCloud | L4: Combined | M4: Combined Pen %
A5: AL | B5: 67 | C5: 461 | D5: 0 | E5: =B5+C5+D5 | F5: 220 | G5: 5 | H5: 4 | I5: 8 | J5: 4 | K5: 4 | L5: =SUM(F5:K5) | M5: =L5/E5
A6: AK | B6: 14 | C6: 148 | D6: 0 | E6: =B6+C6+D6 | F6: 30 | G6: 0 | H6: 8 | I6: 4 | J6: 0 | K6: 0 | L6: =SUM(F6:K6) | M6: =L6/E6
A7: AZ | B7: 15 | C7: 91 | D7: 0 | E7: =B7+C7+D7 | F7: 230 | G7: 8 | H7: 35 | I7: 12 | J7: 4 | K7: 2 | L7: =SUM(F7:K7) | M7: =L7/E7
A8: AR | B8: 75 | C8: 502 | D8: 0 | E8: =B8+C8+D8 | F8: 180 | G8: 5 | H8: 5 | I8: 30 | J8: 4 | K8: 4 | L8: =SUM(F8:K8) | M8: =L8/E8
A9: CA | B9: 58 | C9: 482 | D9: 0 | E9: =B9+C9+D9 | F9: 750 | G9: 12 | H9: 22 | I9: 18 | J9: 8 | K9: 0 | L9: =SUM(F9:K9) | M9: =L9/E9
A10: CO | B10: 62 | C10: 271 | D10: 0 | E10: =B10+C10+D10 | F10: 320 | G10: 10 | H10: 60 | I10: 50 | J10: 4 | K10: 2 | L10: =SUM(F10:K10) | M10: =L10/E10
A11: CT | B11: 0 | C11: 30 | D11: 149 | E11: =B11+C11+D11 | F11: 110 | G11: 4 | H11: 0 | I11: 0 | J11: 6 | K11: 0 | L11: =SUM(F11:K11) | M11: =L11/E11
A12: DE | B12: 3 | C12: 57 | D12: 0 | E12: =B12+C12+D12 | F12: 50 | G12: 2 | H12: 0 | I12: 0 | J12: 4 | K12: 0 | L12: =SUM(F12:K12) | M12: =L12/E12
A13: FL | B13: 66 | C13: 412 | D13: 0 | E13: =B13+C13+D13 | F13: 540 | G13: 18 | H13: 8 | I13: 14 | J13: 14 | K13: 8 | L13: =SUM(F13:K13) | M13: =L13/E13
A14: GA | B14: 153 | C14: 537 | D14: 0 | E14: =B14+C14+D14 | F14: 380 | G14: 12 | H14: 4 | I14: 12 | J14: 12 | K14: 14 | L14: =SUM(F14:K14) | M14: =L14/E14
A15: HI | B15: 3 | C15: 1 | D15: 0 | E15: =B15+C15+D15 | F15: 25 | G15: 0 | H15: 0 | I15: 0 | J15: 0 | K15: 0 | L15: =SUM(F15:K15) | M15: =L15/E15
A16: ID | B16: 44 | C16: 200 | D16: 0 | E16: =B16+C16+D16 | F16: 130 | G16: 8 | H16: 110 | I16: 50 | J16: 0 | K16: 0 | L16: =SUM(F16:K16) | M16: =L16/E16
... A55: DC | B55: 0 | C55: 1 | D55: 0 | E55: =B55+C55+D55 | F55: 10 | G55: 0 | H55: 0 | I55: 0 | J55: 0 | K55: 0 | L55: =SUM(F55:K55) | M55: =L55/E55
A56: US TOTAL | B56: =SUM(B5:B55) | C56: =SUM(C5:C55) | D56: =SUM(D5:D55) | E56: =SUM(E5:E55) | F56: =SUM(F5:F55) | G56: =SUM(G5:G55) | H56: =SUM(H5:H55) | I56: =SUM(I5:I55) | ... L56: =SUM(L5:L55) | M56: =L56/E56
